<?xml version="1.0" encoding="utf-8" ?>
<espForm>
	<configuration>
		<settings>
			<name>cmdb_common_item</name>
			<title>Common Configuration Item Update</title>
			<printTemplates>
			</printTemplates>
			<options>
				<allowResize>true</allowResize>
				<showMenubar>false</showMenubar>
				<showToolbar>true</showToolbar>
				<showStatusBar>false</showStatusBar>
			</options>
		</settings>
		<tables>
			<table>
				<name>config_itemi</name>
				<type>Main Details Table</type>
				<mainDetailsColumn>pk_auto_id</mainDetailsColumn>
				<flags>2</flags>
				<assignments>
				</assignments>
			</table>
		</tables>
		<showMeItems>
		</showMeItems>
		<javascript>
			<methods>
				<method>
					<name>(Globals)</name>
					<code>
						<![CDATA[var strUpdateCIkeys = "";

//-- pointers
function oCI()
{
	return _swdoc.config_itemi;
}

function MF()
{
	return _swdoc.mainform;
}

//-- functions
function setup_form_fields()
{
	//-- get default arguements
	_swdoc.strUpdateCIkeys = _swdoc.GetArg("itemkeys");
	app.g.popuplate_form_fromargs("config_itemi", _swdoc, false);

	//-- get profile text
	var strInfo = "<Multiple Values>";
	if(_swdoc.config_itemi.fk_profilecode!="<Multiple Values>")
	{
		strInfo = app.g.get_key_info("pcdesc",_swdoc.config_itemi.fk_profilecode,"info", "code");
	}
	app._ete(_swdoc.MF().lb_profile , strInfo);
	
	//-- if mult company and contacts then show multiple text (as distinct picklist with display column cant be set)
	app._evi(_swdoc.MF().tb_org_mult, (_swdoc.GetArg("config_itemi.fk_company_id")=="<Multiple Values>"));
	if(_swdoc.MF().tb_org_mult.visible)
	{	
		app._ete(_swdoc.MF().tb_org_mult, "<Multiple Values>");
	}
	else
	{
		//-- have company so set filter
		var strFilter = "_swc_fk_company_id=" + app.pfu(_swdoc.oCI().fk_company_id);
		app._slf(_swdoc.MF().lb_site , strFilter);
		app._slf(_swdoc.MF().lb_contact , strFilter);
	}
	
	app._evi(_swdoc.MF().tb_contact_mult, (_swdoc.GetArg("config_itemi.fk_userdb")=="<Multiple Values>"));
	if(_swdoc.MF().tb_contact_mult.visible)app._ete(_swdoc.MF().tb_contact_mult, "<Multiple Values>");
	
	//-- set auth flag
	app._ete(_swdoc.MF().flg_authorised, (_swdoc.oCI().isauthorised =="No")?0:1);
	
	_swdoc.UpdateFormFromData();
}

//-- when the user changes the type of a CI we need to open the appropriate CI form
function change_config_type(funcCallback)
{
	var strOrigType = _swdoc.oCI().ck_config_type;
	app.cmdb.select_configtype("",true,function(strNewType)
	{
		if(strNewType=="")
		{
			if ((funcCallback != undefined) && (funcCallback != null))
			{
				funcCallback();
			}
		}

		//-- get config type form and if different prompt and if ok save and load correct form
		var strConfirm = "The configuration type may use a different form than that of the current configuration item type(s) and you may lose data. Are you sure you want to change the type?"
		if(!confirm(strConfirm))
		{
			if ((funcCallback != undefined) && (funcCallback != null))
			{
				funcCallback();
			}
		}
	
		if(strOrigType != strNewType)
		{
			_swdoc.oCI().ck_config_type = strNewType;	
			_swdoc.UpdateFormFromData();
		}
	});
	
}]]>
					</code>
				</method>
				<method>
					<name>OnValidate</name>
					<code>
						<![CDATA[OnValidate()
{
	//--
	//-- NWJ - Save form field values to passed in config items

	var arrayCIs = _swdoc.strUpdateCIkeys.split(",");
	for(var x=0; x < arrayCIs.length;x++)
	{
		if(app.g.sqlexecute_formupdate("config_itemi",_swdoc.MF(),arrayCIs[x],false,"<Multiple Values>"))
		{
			/* build vpme relationships
			if(_swdoc.oCI().fk_site != "")    		
			{
				var strRel = dd.GetGlobalParamAsString("Application Settings/CMDB/Types/DefaultSiteCIRelationship");
				var recSite = app.g.get_record("site", _swdoc.oCI().fk_site)
				app.cmdb.generate_meconfigrelation(recSite.fk_cmdb_id,_swdoc.oCI().pk_auto_id, strRel);  
			}
			else
			{
				//-- else form relationship to company (so will see link in vcm company -> customer)
				var strRel = dd.GetGlobalParamAsString("Application Settings/CMDB/Types/DefaultOrgCIRelationship");
				_swdoc.LoadRecordData("swdata", "company", _swdoc.oCI().fk_company_id);    		
   				app.cmdb.generate_meconfigrelation(oCompany().fk_cmdb_id,_swdoc.oCI().pk_auto_id,strRel);  
   			}
   			*/
		
		}
	}
	_swdoc.ResetModiedFlag("config_itemi");
	_swdoc.CloseForm();
	return VALIDATE_FAIL;
}]]>
					</code>
				</method>
			</methods>
		</javascript>
	</configuration>
	<layouts>
		<layout>
			<appearance>
				<width>642</width>
				<height>346</height>
				<backgroundColor>#ffffff</backgroundColor>
				<fillColour>#ffffff</fillColour>
				<textColour >#000000</textColour >
				<font  size="8">Arial</font>
			</appearance>
			<controls>
				<control>
					<general>
						<name>tb_type</name>
						<type>Field</type>
						<group>tabCom:0</group>
					</general>
					<appearance>
						<index>0</index>
						<backgroundColor>#ffffff</backgroundColor>
						<foregroundColor>#000000</foregroundColor>
						<font  size="8">Arial</font>
						<borderStyle>Rectangle</borderStyle>
					</appearance>
					<objectPlacement>
						<position>
							<top>40</top>
							<left>112</left>
							<right>620</right>
							<bottom>58</bottom>
						</position>
						<scaling>
							<top>0</top>
							<left>0</left>
							<right>100</right>
							<bottom>0</bottom>
						</scaling>
					</objectPlacement>
					<data>
						<binding>config_itemi.ck_config_type</binding>
					</data>
					<controlInfo>
						<mouseOverCursor>Window Default</mouseOverCursor>
						<type>Distinct Pick List</type>
						<flags>
							<invisible>false</invisible>
							<readOnly>true</readOnly>
							<mandatory>true</mandatory>
							<mandatoryLabelBackground>false</mandatoryLabelBackground>
							<mandatoryLabelText>false</mandatoryLabelText>
							<allowNullValue>false</allowNullValue>
							<skipTabStop>false</skipTabStop>
							<disabled>false</disabled>
							<protected>false</protected>
							<noMacroExpand>false</noMacroExpand>
							<readOnlyInit>false</readOnlyInit>
							<comboAutoUpdate>false</comboAutoUpdate>
							<comboNewValues>false</comboNewValues>
							<pickListOrderDesc>false</pickListOrderDesc>
						</flags>
						<textLineCount>0</textLineCount>
						<textInputFormat>Text</textInputFormat>
						<properties>
							<hintText>Click here to select the configuration type for these items.</hintText>
							<content>#eeeeee</content>
							<disabledBackgroundColor>#eeeeee</disabledBackgroundColor>
							<sqlSource>swdata</sqlSource>
							<distinctTable>config_typei</distinctTable>
							<distinctColumn>pk_config_type</distinctColumn>
							<dropdownButtonType>1</dropdownButtonType>
							<storedQuery>generic.select</storedQuery>
						</properties>
					</controlInfo>
				</control>
				<control>
					<general>
						<name>lb_profile</name>
						<type>Field</type>
						<group>tabCom:0</group>
					</general>
					<appearance>
						<index>1</index>
						<backgroundColor>#ffffff</backgroundColor>
						<foregroundColor>#000000</foregroundColor>
						<font  size="8">Arial</font>
						<borderStyle>Rectangle</borderStyle>
					</appearance>
					<objectPlacement>
						<position>
							<top>62</top>
							<left>112</left>
							<right>620</right>
							<bottom>80</bottom>
						</position>
						<scaling>
							<top>0</top>
							<left>0</left>
							<right>100</right>
							<bottom>0</bottom>
						</scaling>
					</objectPlacement>
					<data>
					</data>
					<controlInfo>
						<mouseOverCursor>Window Default</mouseOverCursor>
						<type>Distinct Pick List</type>
						<flags>
							<invisible>false</invisible>
							<readOnly>true</readOnly>
							<mandatory>false</mandatory>
							<mandatoryLabelBackground>false</mandatoryLabelBackground>
							<mandatoryLabelText>false</mandatoryLabelText>
							<allowNullValue>false</allowNullValue>
							<skipTabStop>false</skipTabStop>
							<disabled>false</disabled>
							<protected>false</protected>
							<noMacroExpand>false</noMacroExpand>
							<readOnlyInit>false</readOnlyInit>
							<comboAutoUpdate>false</comboAutoUpdate>
							<comboNewValues>false</comboNewValues>
							<pickListOrderDesc>false</pickListOrderDesc>
						</flags>
						<textLineCount>0</textLineCount>
						<textInputFormat>Text</textInputFormat>
						<properties>
							<borderColor>#000000</borderColor>
							<image>#eeeeee</image>
							<sqlSource>swdata</sqlSource>
							<distinctTable>pcdesc</distinctTable>
							<distinctColumn>info</distinctColumn>
							<dropdownButtonType>1</dropdownButtonType>
							<hintText>Click here to select the default profile code for these items</hintText>
							<disabledBackgroundColor>#eeeeee</disabledBackgroundColor>
							<storedQuery>generic.select</storedQuery>
						</properties>
					</controlInfo>
				</control>
				<control>
					<general>
						<name>lb_status</name>
						<type>Field</type>
						<group>tabCom:0</group>
					</general>
					<appearance>
						<index>2</index>
						<backgroundColor>#ffffff</backgroundColor>
						<foregroundColor>#000000</foregroundColor>
						<font  size="8">Arial</font>
						<borderStyle>Rectangle</borderStyle>
					</appearance>
					<objectPlacement>
						<position>
							<top>84</top>
							<left>112</left>
							<right>322</right>
							<bottom>102</bottom>
						</position>
						<scaling>
							<top>0</top>
							<left>0</left>
							<right>50</right>
							<bottom>0</bottom>
						</scaling>
					</objectPlacement>
					<data>
						<binding>config_itemi.fk_status_level</binding>
					</data>
					<controlInfo>
						<mouseOverCursor>Window Default</mouseOverCursor>
						<type>Distinct Pick List</type>
						<flags>
							<invisible>false</invisible>
							<readOnly>false</readOnly>
							<mandatory>true</mandatory>
							<mandatoryLabelBackground>false</mandatoryLabelBackground>
							<mandatoryLabelText>false</mandatoryLabelText>
							<allowNullValue>false</allowNullValue>
							<skipTabStop>false</skipTabStop>
							<disabled>false</disabled>
							<protected>false</protected>
							<noMacroExpand>false</noMacroExpand>
							<readOnlyInit>false</readOnlyInit>
							<comboAutoUpdate>false</comboAutoUpdate>
							<comboNewValues>true</comboNewValues>
							<pickListOrderDesc>false</pickListOrderDesc>
						</flags>
						<textLineCount>0</textLineCount>
						<textInputFormat>Text</textInputFormat>
						<properties>
							<content>#eeeeee</content>
							<sqlSource>swdata</sqlSource>
							<distinctTable>ct_statusl</distinctTable>
							<distinctColumn>status_level</distinctColumn>
							<listFilter>_swc_fk_config_type=&amp;[config_itemi.ck_config_type]</listFilter>
							<disabledBackgroundColor>#eeeeee</disabledBackgroundColor>
							<storedQuery>generic.select</storedQuery>
						</properties>
					</controlInfo>
				</control>
				<control>
					<general>
						<name>Field2</name>
						<type>Field</type>
						<group>tabCom:0</group>
					</general>
					<appearance>
						<index>3</index>
						<backgroundColor>#ffffff</backgroundColor>
						<foregroundColor>#000000</foregroundColor>
						<font  size="8">Arial</font>
						<borderStyle>Rectangle</borderStyle>
					</appearance>
					<objectPlacement>
						<position>
							<top>106</top>
							<left>112</left>
							<right>322</right>
							<bottom>124</bottom>
						</position>
						<scaling>
							<top>0</top>
							<left>0</left>
							<right>50</right>
							<bottom>0</bottom>
						</scaling>
					</objectPlacement>
					<data>
						<binding>config_itemi.fk_impact_level</binding>
					</data>
					<controlInfo>
						<mouseOverCursor>Window Default</mouseOverCursor>
						<type>Distinct Pick List</type>
						<flags>
							<invisible>false</invisible>
							<readOnly>false</readOnly>
							<mandatory>false</mandatory>
							<mandatoryLabelBackground>false</mandatoryLabelBackground>
							<mandatoryLabelText>false</mandatoryLabelText>
							<allowNullValue>false</allowNullValue>
							<skipTabStop>false</skipTabStop>
							<disabled>false</disabled>
							<protected>false</protected>
							<noMacroExpand>false</noMacroExpand>
							<readOnlyInit>false</readOnlyInit>
							<comboAutoUpdate>false</comboAutoUpdate>
							<comboNewValues>true</comboNewValues>
							<pickListOrderDesc>false</pickListOrderDesc>
						</flags>
						<textLineCount>0</textLineCount>
						<textInputFormat>Text</textInputFormat>
						<properties>
							<defaultValue>Low</defaultValue>
							<activeTextColor>#eeeeee</activeTextColor>
							<listItems>None|Low|Medium|High|Critical|</listItems>
							<disabledBackgroundColor>#eeeeee</disabledBackgroundColor>
							<borderColor>#000000</borderColor>
							<sqlSource>swdata</sqlSource>
							<distinctTable>itsm_impact_lvl</distinctTable>
							<distinctColumn>pk_impact</distinctColumn>
							<storedQuery>generic.select</storedQuery>
						</properties>
					</controlInfo>
				</control>
				<control>
					<general>
						<name>Field1</name>
						<type>Field</type>
						<group>tabCom:0</group>
					</general>
					<appearance>
						<index>4</index>
						<backgroundColor>#ffffff</backgroundColor>
						<foregroundColor>#000000</foregroundColor>
						<font  size="8">Arial</font>
						<borderStyle>Rectangle</borderStyle>
					</appearance>
					<objectPlacement>
						<position>
							<top>128</top>
							<left>112</left>
							<right>322</right>
							<bottom>146</bottom>
						</position>
						<scaling>
							<top>0</top>
							<left>0</left>
							<right>50</right>
							<bottom>0</bottom>
						</scaling>
					</objectPlacement>
					<data>
						<binding>config_itemi.fk_urgency_level</binding>
					</data>
					<controlInfo>
						<mouseOverCursor>Window Default</mouseOverCursor>
						<type>Distinct Pick List</type>
						<flags>
							<invisible>false</invisible>
							<readOnly>false</readOnly>
							<mandatory>false</mandatory>
							<mandatoryLabelBackground>false</mandatoryLabelBackground>
							<mandatoryLabelText>false</mandatoryLabelText>
							<allowNullValue>false</allowNullValue>
							<skipTabStop>false</skipTabStop>
							<disabled>false</disabled>
							<protected>false</protected>
							<noMacroExpand>false</noMacroExpand>
							<readOnlyInit>false</readOnlyInit>
							<comboAutoUpdate>false</comboAutoUpdate>
							<comboNewValues>true</comboNewValues>
							<pickListOrderDesc>false</pickListOrderDesc>
						</flags>
						<textLineCount>0</textLineCount>
						<textInputFormat>Text</textInputFormat>
						<properties>
							<defaultValue>Low</defaultValue>
							<activeTextColor>#eeeeee</activeTextColor>
							<listItems>None|Low|Medium|High|Extreme|</listItems>
							<disabledBackgroundColor>#eeeeee</disabledBackgroundColor>
							<borderColor>#000000</borderColor>
							<sqlSource>swdata</sqlSource>
							<distinctTable>itsm_urgency_lvl</distinctTable>
							<distinctColumn>pk_urgency</distinctColumn>
							<storedQuery>generic.select</storedQuery>
						</properties>
					</controlInfo>
				</control>
				<control>
					<general>
						<name>Field1</name>
						<type>Field</type>
						<group>tabCom:0</group>
					</general>
					<appearance>
						<index>5</index>
						<backgroundColor>#ffffff</backgroundColor>
						<foregroundColor>#000000</foregroundColor>
						<font  size="8">Arial</font>
						<borderStyle>Rectangle</borderStyle>
					</appearance>
					<objectPlacement>
						<position>
							<top>151</top>
							<left>112</left>
							<right>322</right>
							<bottom>169</bottom>
						</position>
						<scaling>
							<top>0</top>
							<left>0</left>
							<right>50</right>
							<bottom>0</bottom>
						</scaling>
					</objectPlacement>
					<data>
						<binding>config_itemi.fk_sla</binding>
					</data>
					<controlInfo>
						<mouseOverCursor>Window Default</mouseOverCursor>
						<type>Distinct Pick List</type>
						<flags>
							<invisible>false</invisible>
							<readOnly>false</readOnly>
							<mandatory>false</mandatory>
							<mandatoryLabelBackground>false</mandatoryLabelBackground>
							<mandatoryLabelText>false</mandatoryLabelText>
							<allowNullValue>false</allowNullValue>
							<skipTabStop>false</skipTabStop>
							<disabled>false</disabled>
							<protected>false</protected>
							<noMacroExpand>false</noMacroExpand>
							<readOnlyInit>false</readOnlyInit>
							<comboAutoUpdate>false</comboAutoUpdate>
							<comboNewValues>true</comboNewValues>
							<pickListOrderDesc>false</pickListOrderDesc>
						</flags>
						<textLineCount>0</textLineCount>
						<textInputFormat>Text</textInputFormat>
						<properties>
							<defaultValue>Low</defaultValue>
							<activeTextColor>#eeeeee</activeTextColor>
							<listItems>None|Low|Medium|High|Extreme|</listItems>
							<disabledBackgroundColor>#eeeeee</disabledBackgroundColor>
							<borderColor>#000000</borderColor>
							<sqlSource>syscache</sqlSource>
							<distinctTable>system_sla</distinctTable>
							<distinctColumn>name</distinctColumn>
							<storedQuery>generic.select</storedQuery>
						</properties>
					</controlInfo>
				</control>
				<control>
					<general>
						<name>lb_cmdbstatus</name>
						<type>Field</type>
						<group>tabCom:0</group>
					</general>
					<appearance>
						<index>6</index>
						<backgroundColor>#ffffff</backgroundColor>
						<foregroundColor>#000000</foregroundColor>
						<font  size="8">Arial</font>
						<borderStyle>Rectangle</borderStyle>
					</appearance>
					<objectPlacement>
						<position>
							<top>84</top>
							<left>410</left>
							<right>620</right>
							<bottom>102</bottom>
						</position>
						<scaling>
							<top>0</top>
							<left>50</left>
							<right>100</right>
							<bottom>0</bottom>
						</scaling>
					</objectPlacement>
					<data>
						<binding>config_itemi.cmdb_status</binding>
					</data>
					<controlInfo>
						<mouseOverCursor>Window Default</mouseOverCursor>
						<type>Pick List</type>
						<flags>
							<invisible>false</invisible>
							<readOnly>false</readOnly>
							<mandatory>true</mandatory>
							<mandatoryLabelBackground>false</mandatoryLabelBackground>
							<mandatoryLabelText>false</mandatoryLabelText>
							<allowNullValue>false</allowNullValue>
							<skipTabStop>false</skipTabStop>
							<disabled>true</disabled>
							<protected>false</protected>
							<noMacroExpand>false</noMacroExpand>
							<readOnlyInit>false</readOnlyInit>
							<comboAutoUpdate>false</comboAutoUpdate>
							<comboNewValues>true</comboNewValues>
							<useDDPickList>true</useDDPickList>
						</flags>
						<textLineCount>0</textLineCount>
						<textInputFormat>Text</textInputFormat>
						<properties>
							<content>#eeeeee</content>
							<sqlSource>swdata</sqlSource>
							<distinctTable>ct_statusl</distinctTable>
							<distinctColumn>status_level</distinctColumn>
							<listFilter>fk_config_type = &apos;&amp;[config_item.ck_config_type]&apos;</listFilter>
							<disabledBackgroundColor>#eeeeee</disabledBackgroundColor>
						</properties>
					</controlInfo>
				</control>
				<control>
					<general>
						<name>flg_authorised</name>
						<type>Field</type>
						<flags>
							<transparent>true</transparent>
							<xpStyle>false</xpStyle>
							<hasShadow>false</hasShadow>
							<toolbarButtonStyle>false</toolbarButtonStyle>
							<cache>false</cache>
							<hasBorder>false</hasBorder>
							<hasCheckbox>false</hasCheckbox>
						</flags>
						<group>tabCom:0</group>
					</general>
					<appearance>
						<index>7</index>
						<backgroundColor>#ffffff</backgroundColor>
						<foregroundColor>#000000</foregroundColor>
						<font  size="8">Arial</font>
						<borderStyle>None</borderStyle>
					</appearance>
					<objectPlacement>
						<position>
							<top>106</top>
							<left>406</left>
							<right>632</right>
							<bottom>124</bottom>
						</position>
						<scaling>
							<top>0</top>
							<left>50</left>
							<right>50</right>
							<bottom>0</bottom>
						</scaling>
					</objectPlacement>
					<data>
					</data>
					<controlInfo>
						<mouseOverCursor>Window Default</mouseOverCursor>
						<type>Form Flags</type>
						<textLineCount>0</textLineCount>
						<textInputFormat>Text</textInputFormat>
						<properties>
							<defaultValue>1</defaultValue>
							<content>#eeeeee</content>
							<flagItems>These are authorised configuration items^1|</flagItems>
							<disabledBackgroundColor>#eeeeee</disabledBackgroundColor>
						</properties>
					</controlInfo>
				</control>
				<control>
					<general>
						<name>Field2</name>
						<type>Field</type>
					</general>
					<appearance>
						<index>8</index>
						<backgroundColor>#ffffff</backgroundColor>
						<foregroundColor>#000000</foregroundColor>
						<font  size="8">Arial</font>
						<borderStyle>Rectangle</borderStyle>
					</appearance>
					<objectPlacement>
						<position>
							<top>470</top>
							<left>710</left>
							<right>920</right>
							<bottom>488</bottom>
						</position>
						<scaling>
							<top>0</top>
							<left>0</left>
							<right>50</right>
							<bottom>0</bottom>
						</scaling>
					</objectPlacement>
					<data>
						<binding>config_itemi.fk_supplier</binding>
					</data>
					<controlInfo>
						<mouseOverCursor>Window Default</mouseOverCursor>
						<type>Distinct Pick List</type>
						<flags>
							<invisible>true</invisible>
							<readOnly>false</readOnly>
							<mandatory>false</mandatory>
							<mandatoryLabelBackground>false</mandatoryLabelBackground>
							<mandatoryLabelText>false</mandatoryLabelText>
							<allowNullValue>false</allowNullValue>
							<skipTabStop>false</skipTabStop>
							<disabled>false</disabled>
							<protected>false</protected>
							<noMacroExpand>false</noMacroExpand>
							<readOnlyInit>false</readOnlyInit>
							<comboAutoUpdate>false</comboAutoUpdate>
							<comboNewValues>false</comboNewValues>
							<pickListOrderDesc>false</pickListOrderDesc>
						</flags>
						<textLineCount>0</textLineCount>
						<textInputFormat>Text</textInputFormat>
						<properties>
							<content>#eeeeee</content>
							<newRecordForm>Form.EfSupplier</newRecordForm>
							<disabledBackgroundColor>#eeeeee</disabledBackgroundColor>
							<sqlSource>swdata</sqlSource>
							<distinctTable>supplier</distinctTable>
							<distinctColumn>company_id</distinctColumn>
							<storedQuery>generic.select</storedQuery>
						</properties>
					</controlInfo>
				</control>
				<control>
					<general>
						<name>Field2</name>
						<type>Field</type>
					</general>
					<appearance>
						<index>9</index>
						<backgroundColor>#ffffff</backgroundColor>
						<foregroundColor>#000000</foregroundColor>
						<font  size="8">Arial</font>
						<borderStyle>Rectangle</borderStyle>
					</appearance>
					<objectPlacement>
						<position>
							<top>490</top>
							<left>710</left>
							<right>920</right>
							<bottom>508</bottom>
						</position>
						<scaling>
							<top>0</top>
							<left>0</left>
							<right>50</right>
							<bottom>0</bottom>
						</scaling>
					</objectPlacement>
					<data>
						<binding>config_itemi.fk_manufacturer</binding>
					</data>
					<controlInfo>
						<mouseOverCursor>Window Default</mouseOverCursor>
						<type>Distinct Pick List</type>
						<flags>
							<invisible>true</invisible>
							<readOnly>false</readOnly>
							<mandatory>false</mandatory>
							<mandatoryLabelBackground>false</mandatoryLabelBackground>
							<mandatoryLabelText>false</mandatoryLabelText>
							<allowNullValue>false</allowNullValue>
							<skipTabStop>false</skipTabStop>
							<disabled>false</disabled>
							<protected>false</protected>
							<noMacroExpand>false</noMacroExpand>
							<readOnlyInit>false</readOnlyInit>
							<comboAutoUpdate>false</comboAutoUpdate>
							<comboNewValues>false</comboNewValues>
							<pickListOrderDesc>false</pickListOrderDesc>
						</flags>
						<textLineCount>0</textLineCount>
						<textInputFormat>Text</textInputFormat>
						<properties>
							<content>#eeeeee</content>
							<newRecordForm>Form.EfManufacturer</newRecordForm>
							<disabledBackgroundColor>#eeeeee</disabledBackgroundColor>
							<sqlSource>swdata</sqlSource>
							<distinctTable>manufact</distinctTable>
							<distinctColumn>comp_name</distinctColumn>
							<storedQuery>generic.select</storedQuery>
						</properties>
					</controlInfo>
				</control>
				<control>
					<general>
						<name>Field2</name>
						<type>Field</type>
					</general>
					<appearance>
						<index>10</index>
						<backgroundColor>#ffffff</backgroundColor>
						<foregroundColor>#000000</foregroundColor>
						<font  size="8">Arial</font>
						<borderStyle>Rectangle</borderStyle>
					</appearance>
					<objectPlacement>
						<position>
							<top>510</top>
							<left>710</left>
							<right>920</right>
							<bottom>528</bottom>
						</position>
						<scaling>
							<top>0</top>
							<left>0</left>
							<right>50</right>
							<bottom>0</bottom>
						</scaling>
					</objectPlacement>
					<data>
						<binding>config_itemi.warranty_expiresx</binding>
					</data>
					<controlInfo>
						<mouseOverCursor>Window Default</mouseOverCursor>
						<type>Date/Time Control</type>
						<flags>
							<invisible>true</invisible>
							<readOnly>false</readOnly>
							<mandatory>false</mandatory>
							<mandatoryLabelBackground>false</mandatoryLabelBackground>
							<mandatoryLabelText>false</mandatoryLabelText>
							<allowNullValue>false</allowNullValue>
							<skipTabStop>false</skipTabStop>
							<disabled>false</disabled>
							<protected>false</protected>
							<noMacroExpand>false</noMacroExpand>
							<readOnlyInit>false</readOnlyInit>
							<colorDateIndicator>false</colorDateIndicator>
						</flags>
						<textLineCount>0</textLineCount>
						<textInputFormat>Text</textInputFormat>
						<properties>
							<content>#eeeeee</content>
							<newRecordForm>Form.EfCharge Centre</newRecordForm>
							<disabledBackgroundColor>#eeeeee</disabledBackgroundColor>
							<sqlSource>swdata</sqlSource>
							<distinctTable>costcent</distinctTable>
							<distinctColumn>costcenter</distinctColumn>
							<dateFormatMode>0</dateFormatMode>
						</properties>
					</controlInfo>
				</control>
				<control>
					<general>
						<name>lb_company</name>
						<type>Field</type>
						<group>tabCom:0</group>
					</general>
					<appearance>
						<index>11</index>
						<backgroundColor>#ffffff</backgroundColor>
						<foregroundColor>#000000</foregroundColor>
						<font  size="8">Arial</font>
						<borderStyle>Rectangle</borderStyle>
					</appearance>
					<objectPlacement>
						<position>
							<top>151</top>
							<left>410</left>
							<right>620</right>
							<bottom>169</bottom>
						</position>
						<scaling>
							<top>0</top>
							<left>50</left>
							<right>100</right>
							<bottom>0</bottom>
						</scaling>
					</objectPlacement>
					<data>
						<binding>config_itemi.fk_company_id</binding>
					</data>
					<controlInfo>
						<mouseOverCursor>Window Default</mouseOverCursor>
						<type>Distinct Pick List</type>
						<flags>
							<invisible>false</invisible>
							<readOnly>false</readOnly>
							<mandatory>false</mandatory>
							<mandatoryLabelBackground>false</mandatoryLabelBackground>
							<mandatoryLabelText>false</mandatoryLabelText>
							<allowNullValue>false</allowNullValue>
							<skipTabStop>false</skipTabStop>
							<disabled>false</disabled>
							<protected>false</protected>
							<noMacroExpand>false</noMacroExpand>
							<readOnlyInit>false</readOnlyInit>
							<comboAutoUpdate>false</comboAutoUpdate>
							<comboNewValues>true</comboNewValues>
							<pickListOrderDesc>false</pickListOrderDesc>
						</flags>
						<textLineCount>0</textLineCount>
						<textInputFormat>Text</textInputFormat>
						<properties>
							<content>#eeeeee</content>
							<newRecordForm>Form.EfCharge Centre</newRecordForm>
							<disabledBackgroundColor>#eeeeee</disabledBackgroundColor>
							<sqlSource>swdata</sqlSource>
							<distinctTable>company</distinctTable>
							<distinctColumn>pk_company_id</distinctColumn>
							<displayColumn>companyname</displayColumn>
							<storedQuery>generic.select</storedQuery>
						</properties>
					</controlInfo>
				</control>
				<control>
					<general>
						<name>lb_site</name>
						<type>Field</type>
						<group>tabCom:0</group>
					</general>
					<appearance>
						<index>12</index>
						<backgroundColor>#ffffff</backgroundColor>
						<foregroundColor>#000000</foregroundColor>
						<font  size="8">Arial</font>
						<borderStyle>Rectangle</borderStyle>
					</appearance>
					<objectPlacement>
						<position>
							<top>173</top>
							<left>410</left>
							<right>620</right>
							<bottom>191</bottom>
						</position>
						<scaling>
							<top>0</top>
							<left>50</left>
							<right>100</right>
							<bottom>0</bottom>
						</scaling>
					</objectPlacement>
					<data>
						<binding>config_itemi.fk_site</binding>
					</data>
					<controlInfo>
						<mouseOverCursor>Window Default</mouseOverCursor>
						<type>Distinct Pick List</type>
						<flags>
							<invisible>false</invisible>
							<readOnly>false</readOnly>
							<mandatory>false</mandatory>
							<mandatoryLabelBackground>false</mandatoryLabelBackground>
							<mandatoryLabelText>false</mandatoryLabelText>
							<allowNullValue>false</allowNullValue>
							<skipTabStop>false</skipTabStop>
							<disabled>false</disabled>
							<protected>false</protected>
							<noMacroExpand>false</noMacroExpand>
							<readOnlyInit>false</readOnlyInit>
							<comboAutoUpdate>false</comboAutoUpdate>
							<comboNewValues>true</comboNewValues>
							<pickListOrderDesc>false</pickListOrderDesc>
						</flags>
						<textLineCount>0</textLineCount>
						<textInputFormat>Text</textInputFormat>
						<properties>
							<content>#eeeeee</content>
							<newRecordForm>Form.EfSite</newRecordForm>
							<disabledBackgroundColor>#eeeeee</disabledBackgroundColor>
							<sqlSource>swdata</sqlSource>
							<distinctTable>site</distinctTable>
							<distinctColumn>site_name</distinctColumn>
							<storedQuery>generic.select</storedQuery>
						</properties>
					</controlInfo>
				</control>
				<control>
					<general>
						<name>lb_contact</name>
						<type>Field</type>
						<group>tabCom:0</group>
					</general>
					<appearance>
						<index>13</index>
						<backgroundColor>#ffffff</backgroundColor>
						<foregroundColor>#000000</foregroundColor>
						<font  size="8">Arial</font>
						<borderStyle>Rectangle</borderStyle>
					</appearance>
					<objectPlacement>
						<position>
							<top>195</top>
							<left>410</left>
							<right>620</right>
							<bottom>213</bottom>
						</position>
						<scaling>
							<top>0</top>
							<left>50</left>
							<right>100</right>
							<bottom>0</bottom>
						</scaling>
					</objectPlacement>
					<data>
						<binding>config_itemi.fk_userdb</binding>
					</data>
					<controlInfo>
						<mouseOverCursor>Window Default</mouseOverCursor>
						<type>Distinct Pick List</type>
						<flags>
							<invisible>false</invisible>
							<readOnly>false</readOnly>
							<mandatory>false</mandatory>
							<mandatoryLabelBackground>false</mandatoryLabelBackground>
							<mandatoryLabelText>false</mandatoryLabelText>
							<allowNullValue>false</allowNullValue>
							<skipTabStop>false</skipTabStop>
							<disabled>false</disabled>
							<protected>false</protected>
							<noMacroExpand>false</noMacroExpand>
							<readOnlyInit>false</readOnlyInit>
							<comboAutoUpdate>false</comboAutoUpdate>
							<comboNewValues>true</comboNewValues>
							<pickListOrderDesc>false</pickListOrderDesc>
						</flags>
						<textLineCount>0</textLineCount>
						<textInputFormat>Text</textInputFormat>
						<properties>
							<content>#eeeeee</content>
							<newRecordForm>Form.EfCharge Centre</newRecordForm>
							<disabledBackgroundColor>#eeeeee</disabledBackgroundColor>
							<sqlSource>swdata</sqlSource>
							<distinctTable>userdb</distinctTable>
							<distinctColumn>keysearch</distinctColumn>
							<displayColumn>fullname</displayColumn>
							<storedQuery>generic.select</storedQuery>
						</properties>
					</controlInfo>
				</control>
				<control>
					<general>
						<name>lb_group</name>
						<type>Field</type>
						<group>tabCom:0</group>
					</general>
					<appearance>
						<index>14</index>
						<backgroundColor>#ffffff</backgroundColor>
						<foregroundColor>#000000</foregroundColor>
						<font  size="8">Arial</font>
						<borderStyle>Rectangle</borderStyle>
					</appearance>
					<objectPlacement>
						<position>
							<top>173</top>
							<left>112</left>
							<right>322</right>
							<bottom>191</bottom>
						</position>
						<scaling>
							<top>0</top>
							<left>0</left>
							<right>50</right>
							<bottom>0</bottom>
						</scaling>
					</objectPlacement>
					<data>
						<binding>config_itemi.ci_support_group</binding>
					</data>
					<controlInfo>
						<mouseOverCursor>Window Default</mouseOverCursor>
						<type>Distinct Pick List</type>
						<flags>
							<invisible>false</invisible>
							<readOnly>false</readOnly>
							<mandatory>false</mandatory>
							<mandatoryLabelBackground>false</mandatoryLabelBackground>
							<mandatoryLabelText>false</mandatoryLabelText>
							<allowNullValue>false</allowNullValue>
							<skipTabStop>false</skipTabStop>
							<disabled>false</disabled>
							<protected>false</protected>
							<noMacroExpand>false</noMacroExpand>
							<readOnlyInit>false</readOnlyInit>
							<comboAutoUpdate>false</comboAutoUpdate>
							<comboNewValues>true</comboNewValues>
							<pickListOrderDesc>false</pickListOrderDesc>
						</flags>
						<textLineCount>0</textLineCount>
						<textInputFormat>Text</textInputFormat>
						<properties>
							<content>#eeeeee</content>
							<newRecordForm>Form.EfCharge Centre</newRecordForm>
							<disabledBackgroundColor>#eeeeee</disabledBackgroundColor>
							<sqlSource>syscache</sqlSource>
							<distinctTable>swgroups</distinctTable>
							<distinctColumn>id</distinctColumn>
							<displayColumn>name</displayColumn>
							<storedQuery>generic.select</storedQuery>
						</properties>
					</controlInfo>
				</control>
				<control>
					<general>
						<name>lb_analyst</name>
						<type>Field</type>
						<group>tabCom:0</group>
					</general>
					<appearance>
						<index>15</index>
						<backgroundColor>#ffffff</backgroundColor>
						<foregroundColor>#000000</foregroundColor>
						<font  size="8">Arial</font>
						<borderStyle>Rectangle</borderStyle>
					</appearance>
					<objectPlacement>
						<position>
							<top>195</top>
							<left>112</left>
							<right>322</right>
							<bottom>213</bottom>
						</position>
						<scaling>
							<top>0</top>
							<left>0</left>
							<right>50</right>
							<bottom>0</bottom>
						</scaling>
					</objectPlacement>
					<data>
						<binding>config_itemi.ci_support_analyst</binding>
					</data>
					<controlInfo>
						<mouseOverCursor>Window Default</mouseOverCursor>
						<type>Distinct Pick List</type>
						<textLineCount>0</textLineCount>
						<textInputFormat>Text</textInputFormat>
						<properties>
							<content>#eeeeee</content>
							<newRecordForm>Form.EfCharge Centre</newRecordForm>
							<disabledBackgroundColor>#eeeeee</disabledBackgroundColor>
							<sqlSource>syscache</sqlSource>
							<distinctTable>swanalysts</distinctTable>
							<distinctColumn>AnalystID</distinctColumn>
							<displayColumn>Name</displayColumn>
							<listFilter>_swc_supportgroup=&amp;[config_itemi.ci_support_group]&amp;_swc_class=1</listFilter>
							<storedQuery>generic.select</storedQuery>
						</properties>
					</controlInfo>
				</control>
				<control>
					<general>
						<name>tabCom</name>
						<type>TabControl</type>
						<flags>
							<transparent>true</transparent>
							<xpStyle>false</xpStyle>
							<hasShadow>false</hasShadow>
							<toolbarButtonStyle>false</toolbarButtonStyle>
							<cache>false</cache>
							<hasBorder>false</hasBorder>
							<hasCheckbox>false</hasCheckbox>
						</flags>
					</general>
					<appearance>
						<index>16</index>
						<caption>Tab1</caption>
						<backgroundColor>#ded7ce</backgroundColor>
						<foregroundColor>#ffffff</foregroundColor>
						<font  size="8">Arial</font>
						<borderStyle>None</borderStyle>
					</appearance>
					<objectPlacement>
						<position>
							<top>10</top>
							<left>10</left>
							<right>635</right>
							<bottom>338</bottom>
						</position>
						<scaling>
							<top>0</top>
							<left>0</left>
							<right>100</right>
							<bottom>100</bottom>
						</scaling>
					</objectPlacement>
					<data>
					</data>
					<tabStyle>Top</tabStyle>
					<tabSize>19</tabSize>
					<items>
						<item>
							<name>Common Details</name>
							<properties>56=#dddddd|59=#5f5f5f|_flags=0</properties>
							<textBorder>None</textBorder>
							<textBackgroundColor>#ffffff</textBackgroundColor>
							<controlInfo>
								<mouseOverCursor>Window Default</mouseOverCursor>
								<properties>
									<tabColor>#dddddd</tabColor>
									<inactiveTextColor>#5f5f5f</inactiveTextColor>
								</properties>
							</controlInfo>
						</item>
					</items>
					<selectedTextFont  size="8">Arial</selectedTextFont>
					<selectedTextColor>#000000</selectedTextColor>
					<deselectedTextColor>#000000</deselectedTextColor>
					<tabSlopeLeft>2</tabSlopeLeft>
					<tabSlopeRight>2</tabSlopeRight>
					<deselectedTabHeightOffset>1</deselectedTabHeightOffset>
					<tabSpacing>0</tabSpacing>
					<controlInfo>
						<mouseOverCursor>Window Default</mouseOverCursor>
						<properties>
							<tabStyle>0</tabStyle>
						</properties>
					</controlInfo>
				</control>
				<control>
					<general>
						<name>Label2</name>
						<type>FieldName</type>
						<flags>
							<transparent>true</transparent>
							<xpStyle>false</xpStyle>
							<hasShadow>false</hasShadow>
							<toolbarButtonStyle>false</toolbarButtonStyle>
							<cache>false</cache>
							<hasBorder>false</hasBorder>
							<hasCheckbox>false</hasCheckbox>
						</flags>
						<group>tabCom:0</group>
					</general>
					<appearance>
						<index>17</index>
						<caption>Type</caption>
						<backgroundColor>#ffffff</backgroundColor>
						<foregroundColor>#000000</foregroundColor>
						<font  size="8">Arial</font>
						<alignment>Right</alignment>
						<borderStyle>None</borderStyle>
						<fillStyle>Solid</fillStyle>
					</appearance>
					<objectPlacement>
						<position>
							<top>39</top>
							<left>31</left>
							<right>108</right>
							<bottom>57</bottom>
						</position>
						<scaling>
							<top>0</top>
							<left>0</left>
							<right>0</right>
							<bottom>0</bottom>
						</scaling>
					</objectPlacement>
					<data>
						<binding>config_itemi.ck_config_type</binding>
					</data>
					<controlInfo>
						<mouseOverCursor>Window Default</mouseOverCursor>
						<properties>
						</properties>
					</controlInfo>
				</control>
				<control>
					<general>
						<name>Label4</name>
						<type>FieldName</type>
						<flags>
							<transparent>true</transparent>
							<xpStyle>false</xpStyle>
							<hasShadow>false</hasShadow>
							<toolbarButtonStyle>false</toolbarButtonStyle>
							<cache>false</cache>
							<hasBorder>false</hasBorder>
							<hasCheckbox>false</hasCheckbox>
						</flags>
						<group>tabCom:0</group>
					</general>
					<appearance>
						<index>18</index>
						<caption>Priority</caption>
						<backgroundColor>#ffffff</backgroundColor>
						<foregroundColor>#000000</foregroundColor>
						<font  size="8">Arial</font>
						<alignment>Right</alignment>
						<borderStyle>None</borderStyle>
						<fillStyle>Solid</fillStyle>
					</appearance>
					<objectPlacement>
						<position>
							<top>151</top>
							<left>31</left>
							<right>108</right>
							<bottom>169</bottom>
						</position>
						<scaling>
							<top>0</top>
							<left>0</left>
							<right>0</right>
							<bottom>0</bottom>
						</scaling>
					</objectPlacement>
					<data>
						<binding>config_itemi.fk_sla</binding>
					</data>
					<controlInfo>
						<mouseOverCursor>Window Default</mouseOverCursor>
						<properties>
						</properties>
					</controlInfo>
				</control>
				<control>
					<general>
						<name>Label2</name>
						<type>FieldName</type>
						<flags>
							<transparent>true</transparent>
							<xpStyle>false</xpStyle>
							<hasShadow>false</hasShadow>
							<toolbarButtonStyle>false</toolbarButtonStyle>
							<cache>false</cache>
							<hasBorder>false</hasBorder>
							<hasCheckbox>false</hasCheckbox>
						</flags>
						<group>tabCom:0</group>
					</general>
					<appearance>
						<index>19</index>
						<caption>Status</caption>
						<backgroundColor>#ffffff</backgroundColor>
						<foregroundColor>#000000</foregroundColor>
						<font  size="8">Arial</font>
						<alignment>Right</alignment>
						<borderStyle>None</borderStyle>
						<fillStyle>Solid</fillStyle>
					</appearance>
					<objectPlacement>
						<position>
							<top>84</top>
							<left>31</left>
							<right>108</right>
							<bottom>102</bottom>
						</position>
						<scaling>
							<top>0</top>
							<left>0</left>
							<right>0</right>
							<bottom>0</bottom>
						</scaling>
					</objectPlacement>
					<data>
						<binding>config_itemi.fk_status_level</binding>
					</data>
					<controlInfo>
						<mouseOverCursor>Window Default</mouseOverCursor>
						<properties>
						</properties>
					</controlInfo>
				</control>
				<control>
					<general>
						<name>Label2</name>
						<type>FieldName</type>
						<flags>
							<transparent>true</transparent>
							<xpStyle>false</xpStyle>
							<hasShadow>false</hasShadow>
							<toolbarButtonStyle>false</toolbarButtonStyle>
							<cache>false</cache>
							<hasBorder>false</hasBorder>
							<hasCheckbox>false</hasCheckbox>
						</flags>
						<group>tabCom:0</group>
					</general>
					<appearance>
						<index>20</index>
						<caption>Impact</caption>
						<backgroundColor>#ffffff</backgroundColor>
						<foregroundColor>#000000</foregroundColor>
						<font  size="8">Arial</font>
						<alignment>Right</alignment>
						<borderStyle>None</borderStyle>
						<fillStyle>Solid</fillStyle>
					</appearance>
					<objectPlacement>
						<position>
							<top>106</top>
							<left>31</left>
							<right>108</right>
							<bottom>124</bottom>
						</position>
						<scaling>
							<top>0</top>
							<left>0</left>
							<right>0</right>
							<bottom>0</bottom>
						</scaling>
					</objectPlacement>
					<data>
						<binding>config_itemi.fk_impact_level</binding>
					</data>
					<controlInfo>
						<mouseOverCursor>Window Default</mouseOverCursor>
						<properties>
						</properties>
					</controlInfo>
				</control>
				<control>
					<general>
						<name>Label2</name>
						<type>FieldName</type>
						<flags>
							<transparent>true</transparent>
							<xpStyle>false</xpStyle>
							<hasShadow>false</hasShadow>
							<toolbarButtonStyle>false</toolbarButtonStyle>
							<cache>false</cache>
							<hasBorder>false</hasBorder>
							<hasCheckbox>false</hasCheckbox>
						</flags>
						<group>tabCom:0</group>
					</general>
					<appearance>
						<index>21</index>
						<caption>Urgency</caption>
						<backgroundColor>#ffffff</backgroundColor>
						<foregroundColor>#000000</foregroundColor>
						<font  size="8">Arial</font>
						<alignment>Right</alignment>
						<borderStyle>None</borderStyle>
						<fillStyle>Solid</fillStyle>
					</appearance>
					<objectPlacement>
						<position>
							<top>128</top>
							<left>31</left>
							<right>108</right>
							<bottom>146</bottom>
						</position>
						<scaling>
							<top>0</top>
							<left>0</left>
							<right>0</right>
							<bottom>0</bottom>
						</scaling>
					</objectPlacement>
					<data>
						<binding>config_itemi.fk_urgency_level</binding>
					</data>
					<controlInfo>
						<mouseOverCursor>Window Default</mouseOverCursor>
						<properties>
						</properties>
					</controlInfo>
				</control>
				<control>
					<general>
						<name>Label1</name>
						<type>FieldName</type>
						<flags>
							<transparent>true</transparent>
							<xpStyle>false</xpStyle>
							<hasShadow>false</hasShadow>
							<toolbarButtonStyle>false</toolbarButtonStyle>
							<cache>false</cache>
							<hasBorder>false</hasBorder>
							<hasCheckbox>false</hasCheckbox>
						</flags>
						<group>tabCom:0</group>
					</general>
					<appearance>
						<index>22</index>
						<caption>Category</caption>
						<backgroundColor>#dddddd</backgroundColor>
						<foregroundColor>#000000</foregroundColor>
						<font  size="8">Arial</font>
						<alignment>Right</alignment>
						<borderStyle>None</borderStyle>
						<fillStyle>Solid</fillStyle>
					</appearance>
					<objectPlacement>
						<position>
							<top>62</top>
							<left>31</left>
							<right>108</right>
							<bottom>80</bottom>
						</position>
						<scaling>
							<top>0</top>
							<left>0</left>
							<right>0</right>
							<bottom>0</bottom>
						</scaling>
					</objectPlacement>
					<data>
						<binding>config_itemi.fk_profilecode</binding>
					</data>
					<controlInfo>
						<mouseOverCursor>Window Default</mouseOverCursor>
						<properties>
						</properties>
					</controlInfo>
				</control>
				<control>
					<general>
						<name>Label2</name>
						<type>FieldName</type>
						<flags>
							<transparent>true</transparent>
							<xpStyle>false</xpStyle>
							<hasShadow>false</hasShadow>
							<toolbarButtonStyle>false</toolbarButtonStyle>
							<cache>false</cache>
							<hasBorder>false</hasBorder>
							<hasCheckbox>false</hasCheckbox>
						</flags>
					</general>
					<appearance>
						<index>23</index>
						<caption>Supplier</caption>
						<backgroundColor>#ffffff</backgroundColor>
						<foregroundColor>#000000</foregroundColor>
						<font  size="8">Arial</font>
						<alignment>Right</alignment>
						<borderStyle>None</borderStyle>
						<fillStyle>Solid</fillStyle>
					</appearance>
					<objectPlacement>
						<position>
							<top>470</top>
							<left>630</left>
							<right>707</right>
							<bottom>488</bottom>
						</position>
						<scaling>
							<top>0</top>
							<left>0</left>
							<right>0</right>
							<bottom>0</bottom>
						</scaling>
					</objectPlacement>
					<data>
						<binding>config_itemi.fk_supplier</binding>
					</data>
					<controlInfo>
						<mouseOverCursor>Window Default</mouseOverCursor>
						<flags>
							<invisible>true</invisible>
							<skipTabStop>false</skipTabStop>
							<disabled>false</disabled>
							<protected>false</protected>
							<noMacroExpand>false</noMacroExpand>
							<multiLine>false</multiLine>
						</flags>
						<properties>
						</properties>
					</controlInfo>
				</control>
				<control>
					<general>
						<name>Label2</name>
						<type>FieldName</type>
						<flags>
							<transparent>true</transparent>
							<xpStyle>false</xpStyle>
							<hasShadow>false</hasShadow>
							<toolbarButtonStyle>false</toolbarButtonStyle>
							<cache>false</cache>
							<hasBorder>false</hasBorder>
							<hasCheckbox>false</hasCheckbox>
						</flags>
					</general>
					<appearance>
						<index>24</index>
						<caption>Manufacturer</caption>
						<backgroundColor>#ffffff</backgroundColor>
						<foregroundColor>#000000</foregroundColor>
						<font  size="8">Arial</font>
						<alignment>Right</alignment>
						<borderStyle>None</borderStyle>
						<fillStyle>Solid</fillStyle>
					</appearance>
					<objectPlacement>
						<position>
							<top>490</top>
							<left>630</left>
							<right>707</right>
							<bottom>508</bottom>
						</position>
						<scaling>
							<top>0</top>
							<left>0</left>
							<right>0</right>
							<bottom>0</bottom>
						</scaling>
					</objectPlacement>
					<data>
						<binding>config_itemi.fk_manufacturer</binding>
					</data>
					<controlInfo>
						<mouseOverCursor>Window Default</mouseOverCursor>
						<flags>
							<invisible>true</invisible>
							<skipTabStop>false</skipTabStop>
							<disabled>false</disabled>
							<protected>false</protected>
							<noMacroExpand>false</noMacroExpand>
							<multiLine>false</multiLine>
						</flags>
						<properties>
						</properties>
					</controlInfo>
				</control>
				<control>
					<general>
						<name>Label2</name>
						<type>FieldName</type>
						<flags>
							<transparent>true</transparent>
							<xpStyle>false</xpStyle>
							<hasShadow>false</hasShadow>
							<toolbarButtonStyle>false</toolbarButtonStyle>
							<cache>false</cache>
							<hasBorder>false</hasBorder>
							<hasCheckbox>false</hasCheckbox>
						</flags>
						<group>tabCom:0</group>
					</general>
					<appearance>
						<index>25</index>
						<caption>Support Group</caption>
						<backgroundColor>#ffffff</backgroundColor>
						<foregroundColor>#000000</foregroundColor>
						<font  size="8">Arial</font>
						<alignment>Right</alignment>
						<borderStyle>None</borderStyle>
						<fillStyle>Solid</fillStyle>
					</appearance>
					<objectPlacement>
						<position>
							<top>173</top>
							<left>31</left>
							<right>108</right>
							<bottom>191</bottom>
						</position>
						<scaling>
							<top>0</top>
							<left>0</left>
							<right>0</right>
							<bottom>0</bottom>
						</scaling>
					</objectPlacement>
					<data>
						<binding>config_itemi.ci_support_group</binding>
					</data>
					<controlInfo>
						<mouseOverCursor>Window Default</mouseOverCursor>
						<properties>
						</properties>
					</controlInfo>
				</control>
				<control>
					<general>
						<name>Label2</name>
						<type>FieldName</type>
						<flags>
							<transparent>true</transparent>
							<xpStyle>false</xpStyle>
							<hasShadow>false</hasShadow>
							<toolbarButtonStyle>false</toolbarButtonStyle>
							<cache>false</cache>
							<hasBorder>false</hasBorder>
							<hasCheckbox>false</hasCheckbox>
						</flags>
						<group>tabCom:0</group>
					</general>
					<appearance>
						<index>26</index>
						<caption>Support Analyst</caption>
						<backgroundColor>#ffffff</backgroundColor>
						<foregroundColor>#000000</foregroundColor>
						<font  size="8">Arial</font>
						<alignment>Right</alignment>
						<borderStyle>None</borderStyle>
						<fillStyle>Solid</fillStyle>
					</appearance>
					<objectPlacement>
						<position>
							<top>195</top>
							<left>18</left>
							<right>108</right>
							<bottom>213</bottom>
						</position>
						<scaling>
							<top>0</top>
							<left>0</left>
							<right>0</right>
							<bottom>0</bottom>
						</scaling>
					</objectPlacement>
					<data>
						<binding>config_itemi.ci_support_analyst</binding>
					</data>
					<controlInfo>
						<mouseOverCursor>Window Default</mouseOverCursor>
						<properties>
						</properties>
					</controlInfo>
				</control>
				<control>
					<general>
						<name>Label2</name>
						<type>FieldName</type>
						<flags>
							<transparent>true</transparent>
							<xpStyle>false</xpStyle>
							<hasShadow>false</hasShadow>
							<toolbarButtonStyle>false</toolbarButtonStyle>
							<cache>false</cache>
							<hasBorder>false</hasBorder>
							<hasCheckbox>false</hasCheckbox>
						</flags>
						<group>tabCom:0</group>
					</general>
					<appearance>
						<index>27</index>
						<caption>Contact</caption>
						<backgroundColor>#ffffff</backgroundColor>
						<foregroundColor>#000000</foregroundColor>
						<font  size="8">Arial</font>
						<alignment>Right</alignment>
						<borderStyle>None</borderStyle>
						<fillStyle>Solid</fillStyle>
					</appearance>
					<objectPlacement>
						<position>
							<top>195</top>
							<left>329</left>
							<right>406</right>
							<bottom>213</bottom>
						</position>
						<scaling>
							<top>0</top>
							<left>50</left>
							<right>50</right>
							<bottom>0</bottom>
						</scaling>
					</objectPlacement>
					<data>
						<binding>config_itemi.fk_userdb</binding>
					</data>
					<controlInfo>
						<mouseOverCursor>Window Default</mouseOverCursor>
						<properties>
						</properties>
					</controlInfo>
				</control>
				<control>
					<general>
						<name>Label2</name>
						<type>FieldName</type>
						<flags>
							<transparent>true</transparent>
							<xpStyle>false</xpStyle>
							<hasShadow>false</hasShadow>
							<toolbarButtonStyle>false</toolbarButtonStyle>
							<cache>false</cache>
							<hasBorder>false</hasBorder>
							<hasCheckbox>false</hasCheckbox>
						</flags>
					</general>
					<appearance>
						<index>28</index>
						<caption>Warranty Expires</caption>
						<backgroundColor>#ffffff</backgroundColor>
						<foregroundColor>#000000</foregroundColor>
						<font  size="8">Arial</font>
						<alignment>Right</alignment>
						<borderStyle>None</borderStyle>
						<fillStyle>Solid</fillStyle>
					</appearance>
					<objectPlacement>
						<position>
							<top>510</top>
							<left>620</left>
							<right>710</right>
							<bottom>528</bottom>
						</position>
						<scaling>
							<top>0</top>
							<left>0</left>
							<right>0</right>
							<bottom>0</bottom>
						</scaling>
					</objectPlacement>
					<data>
						<binding>config_itemi.warranty_expiresx</binding>
					</data>
					<controlInfo>
						<mouseOverCursor>Window Default</mouseOverCursor>
						<flags>
							<invisible>true</invisible>
							<skipTabStop>false</skipTabStop>
							<disabled>false</disabled>
							<protected>false</protected>
							<noMacroExpand>false</noMacroExpand>
							<multiLine>false</multiLine>
						</flags>
						<properties>
						</properties>
					</controlInfo>
				</control>
				<control>
					<general>
						<name>Label2</name>
						<type>FieldName</type>
						<flags>
							<transparent>true</transparent>
							<xpStyle>false</xpStyle>
							<hasShadow>false</hasShadow>
							<toolbarButtonStyle>false</toolbarButtonStyle>
							<cache>false</cache>
							<hasBorder>false</hasBorder>
							<hasCheckbox>false</hasCheckbox>
						</flags>
						<group>tabCom:0</group>
					</general>
					<appearance>
						<index>29</index>
						<caption>Site</caption>
						<backgroundColor>#ffffff</backgroundColor>
						<foregroundColor>#000000</foregroundColor>
						<font  size="8">Arial</font>
						<alignment>Right</alignment>
						<borderStyle>None</borderStyle>
						<fillStyle>Solid</fillStyle>
					</appearance>
					<objectPlacement>
						<position>
							<top>173</top>
							<left>329</left>
							<right>406</right>
							<bottom>191</bottom>
						</position>
						<scaling>
							<top>0</top>
							<left>50</left>
							<right>50</right>
							<bottom>0</bottom>
						</scaling>
					</objectPlacement>
					<data>
						<binding>config_itemi.fk_site</binding>
					</data>
					<controlInfo>
						<mouseOverCursor>Window Default</mouseOverCursor>
						<properties>
						</properties>
					</controlInfo>
				</control>
				<control>
					<general>
						<name>Label2</name>
						<type>FieldName</type>
						<flags>
							<transparent>true</transparent>
							<xpStyle>false</xpStyle>
							<hasShadow>false</hasShadow>
							<toolbarButtonStyle>false</toolbarButtonStyle>
							<cache>false</cache>
							<hasBorder>false</hasBorder>
							<hasCheckbox>false</hasCheckbox>
						</flags>
						<group>tabCom:0</group>
					</general>
					<appearance>
						<index>30</index>
						<caption>CMDB Status</caption>
						<backgroundColor>#ffffff</backgroundColor>
						<foregroundColor>#000000</foregroundColor>
						<font  size="8">Arial</font>
						<alignment>Right</alignment>
						<borderStyle>None</borderStyle>
						<fillStyle>Solid</fillStyle>
					</appearance>
					<objectPlacement>
						<position>
							<top>84</top>
							<left>329</left>
							<right>406</right>
							<bottom>102</bottom>
						</position>
						<scaling>
							<top>0</top>
							<left>50</left>
							<right>50</right>
							<bottom>0</bottom>
						</scaling>
					</objectPlacement>
					<data>
						<binding>config_itemi.cmdb_status</binding>
					</data>
					<controlInfo>
						<mouseOverCursor>Window Default</mouseOverCursor>
						<properties>
						</properties>
					</controlInfo>
				</control>
				<control>
					<general>
						<name>Label5</name>
						<type>FieldName</type>
						<flags>
							<transparent>true</transparent>
							<xpStyle>false</xpStyle>
							<hasShadow>false</hasShadow>
							<toolbarButtonStyle>false</toolbarButtonStyle>
							<cache>false</cache>
							<hasBorder>false</hasBorder>
							<hasCheckbox>false</hasCheckbox>
						</flags>
					</general>
					<appearance>
						<index>31</index>
						<caption>Is active?</caption>
						<backgroundColor>#ffffff</backgroundColor>
						<foregroundColor>#000000</foregroundColor>
						<font  size="8">Arial</font>
						<alignment>Left</alignment>
						<borderStyle>None</borderStyle>
						<fillStyle>Solid</fillStyle>
					</appearance>
					<objectPlacement>
						<position>
							<top>212</top>
							<left>760</left>
							<right>814</right>
							<bottom>228</bottom>
						</position>
						<scaling>
							<top>0</top>
							<left>0</left>
							<right>0</right>
							<bottom>0</bottom>
						</scaling>
					</objectPlacement>
					<data>
						<binding>config_itemi.isactive</binding>
					</data>
					<controlInfo>
						<mouseOverCursor>Window Default</mouseOverCursor>
						<flags>
							<invisible>true</invisible>
							<skipTabStop>false</skipTabStop>
							<disabled>false</disabled>
							<protected>true</protected>
							<noMacroExpand>false</noMacroExpand>
							<multiLine>false</multiLine>
						</flags>
						<properties>
						</properties>
					</controlInfo>
				</control>
				<control>
					<general>
						<name>Field5</name>
						<type>Field</type>
					</general>
					<appearance>
						<index>32</index>
						<backgroundColor>#ffffff</backgroundColor>
						<foregroundColor>#000000</foregroundColor>
						<font  size="8">Arial</font>
						<borderStyle>3-D Sunken</borderStyle>
					</appearance>
					<objectPlacement>
						<position>
							<top>212</top>
							<left>814</left>
							<right>906</right>
							<bottom>228</bottom>
						</position>
						<scaling>
							<top>0</top>
							<left>0</left>
							<right>0</right>
							<bottom>0</bottom>
						</scaling>
					</objectPlacement>
					<data>
						<binding>config_itemi.isactive</binding>
					</data>
					<controlInfo>
						<mouseOverCursor>Window Default</mouseOverCursor>
						<type>Text Edit</type>
						<flags>
							<invisible>true</invisible>
							<readOnly>false</readOnly>
							<mandatory>false</mandatory>
							<mandatoryLabelBackground>false</mandatoryLabelBackground>
							<mandatoryLabelText>false</mandatoryLabelText>
							<allowNullValue>false</allowNullValue>
							<skipTabStop>false</skipTabStop>
							<disabled>false</disabled>
							<protected>true</protected>
							<noMacroExpand>false</noMacroExpand>
							<readOnlyInit>false</readOnlyInit>
							<autoCompleteField>false</autoCompleteField>
							<editUnlimitedText>false</editUnlimitedText>
							<url>false</url>
						</flags>
						<textLineCount>0</textLineCount>
						<textInputFormat>Text</textInputFormat>
						<properties>
							<content>#eeeeee</content>
							<disabledBackgroundColor>#eeeeee</disabledBackgroundColor>
						</properties>
					</controlInfo>
				</control>
				<control>
					<general>
						<name>Label6</name>
						<type>FieldName</type>
						<flags>
							<transparent>true</transparent>
							<xpStyle>false</xpStyle>
							<hasShadow>false</hasShadow>
							<toolbarButtonStyle>false</toolbarButtonStyle>
							<cache>false</cache>
							<hasBorder>false</hasBorder>
							<hasCheckbox>false</hasCheckbox>
						</flags>
					</general>
					<appearance>
						<index>33</index>
						<caption>Is authorised?</caption>
						<backgroundColor>#ffffff</backgroundColor>
						<foregroundColor>#000000</foregroundColor>
						<font  size="8">Arial</font>
						<alignment>Left</alignment>
						<borderStyle>None</borderStyle>
						<fillStyle>Solid</fillStyle>
					</appearance>
					<objectPlacement>
						<position>
							<top>241</top>
							<left>737</left>
							<right>813</right>
							<bottom>257</bottom>
						</position>
						<scaling>
							<top>0</top>
							<left>0</left>
							<right>0</right>
							<bottom>0</bottom>
						</scaling>
					</objectPlacement>
					<data>
						<binding>config_itemi.isauthorised</binding>
					</data>
					<controlInfo>
						<mouseOverCursor>Window Default</mouseOverCursor>
						<flags>
							<invisible>true</invisible>
							<skipTabStop>false</skipTabStop>
							<disabled>false</disabled>
							<protected>true</protected>
							<noMacroExpand>false</noMacroExpand>
							<multiLine>false</multiLine>
						</flags>
						<properties>
						</properties>
					</controlInfo>
				</control>
				<control>
					<general>
						<name>Field6</name>
						<type>Field</type>
					</general>
					<appearance>
						<index>34</index>
						<backgroundColor>#ffffff</backgroundColor>
						<foregroundColor>#000000</foregroundColor>
						<font  size="8">Arial</font>
						<borderStyle>3-D Sunken</borderStyle>
					</appearance>
					<objectPlacement>
						<position>
							<top>241</top>
							<left>813</left>
							<right>841</right>
							<bottom>257</bottom>
						</position>
						<scaling>
							<top>0</top>
							<left>0</left>
							<right>0</right>
							<bottom>0</bottom>
						</scaling>
					</objectPlacement>
					<data>
						<binding>config_itemi.isauthorised</binding>
					</data>
					<controlInfo>
						<mouseOverCursor>Window Default</mouseOverCursor>
						<type>Text Edit</type>
						<flags>
							<invisible>true</invisible>
							<readOnly>false</readOnly>
							<mandatory>false</mandatory>
							<mandatoryLabelBackground>false</mandatoryLabelBackground>
							<mandatoryLabelText>false</mandatoryLabelText>
							<allowNullValue>false</allowNullValue>
							<skipTabStop>false</skipTabStop>
							<disabled>false</disabled>
							<protected>true</protected>
							<noMacroExpand>false</noMacroExpand>
							<readOnlyInit>false</readOnlyInit>
							<autoCompleteField>false</autoCompleteField>
							<editUnlimitedText>false</editUnlimitedText>
							<url>false</url>
						</flags>
						<textLineCount>0</textLineCount>
						<textInputFormat>Text</textInputFormat>
						<properties>
							<content>#eeeeee</content>
							<disabledBackgroundColor>#eeeeee</disabledBackgroundColor>
						</properties>
					</controlInfo>
				</control>
				<control>
					<general>
						<name>Label3</name>
						<type>FieldName</type>
						<flags>
							<transparent>true</transparent>
							<xpStyle>false</xpStyle>
							<hasShadow>false</hasShadow>
							<toolbarButtonStyle>false</toolbarButtonStyle>
							<cache>false</cache>
							<hasBorder>false</hasBorder>
							<hasCheckbox>false</hasCheckbox>
						</flags>
					</general>
					<appearance>
						<index>35</index>
						<caption>Is de-activated?</caption>
						<backgroundColor>#ffffff</backgroundColor>
						<foregroundColor>#000000</foregroundColor>
						<font  size="8">Arial</font>
						<alignment>Left</alignment>
						<borderStyle>None</borderStyle>
						<fillStyle>Solid</fillStyle>
					</appearance>
					<objectPlacement>
						<position>
							<top>135</top>
							<left>710</left>
							<right>795</right>
							<bottom>151</bottom>
						</position>
						<scaling>
							<top>0</top>
							<left>0</left>
							<right>0</right>
							<bottom>0</bottom>
						</scaling>
					</objectPlacement>
					<data>
						<binding>config_itemi.isdeactivated</binding>
					</data>
					<controlInfo>
						<mouseOverCursor>Window Default</mouseOverCursor>
						<flags>
							<invisible>true</invisible>
							<skipTabStop>false</skipTabStop>
							<disabled>false</disabled>
							<protected>true</protected>
							<noMacroExpand>false</noMacroExpand>
							<multiLine>false</multiLine>
						</flags>
						<properties>
						</properties>
					</controlInfo>
				</control>
				<control>
					<general>
						<name>Field4</name>
						<type>Field</type>
					</general>
					<appearance>
						<index>36</index>
						<backgroundColor>#ffffff</backgroundColor>
						<foregroundColor>#000000</foregroundColor>
						<font  size="8">Arial</font>
						<borderStyle>3-D Sunken</borderStyle>
					</appearance>
					<objectPlacement>
						<position>
							<top>135</top>
							<left>795</left>
							<right>823</right>
							<bottom>151</bottom>
						</position>
						<scaling>
							<top>0</top>
							<left>0</left>
							<right>0</right>
							<bottom>0</bottom>
						</scaling>
					</objectPlacement>
					<data>
						<binding>config_itemi.isdeactivated</binding>
					</data>
					<controlInfo>
						<mouseOverCursor>Window Default</mouseOverCursor>
						<type>Text Edit</type>
						<flags>
							<invisible>true</invisible>
							<readOnly>false</readOnly>
							<mandatory>false</mandatory>
							<mandatoryLabelBackground>false</mandatoryLabelBackground>
							<mandatoryLabelText>false</mandatoryLabelText>
							<allowNullValue>false</allowNullValue>
							<skipTabStop>false</skipTabStop>
							<disabled>false</disabled>
							<protected>true</protected>
							<noMacroExpand>false</noMacroExpand>
							<readOnlyInit>false</readOnlyInit>
							<autoCompleteField>false</autoCompleteField>
							<editUnlimitedText>false</editUnlimitedText>
							<url>false</url>
						</flags>
						<textLineCount>0</textLineCount>
						<textInputFormat>Text</textInputFormat>
						<properties>
							<content>#eeeeee</content>
							<disabledBackgroundColor>#eeeeee</disabledBackgroundColor>
						</properties>
					</controlInfo>
				</control>
				<control>
					<general>
						<name>Label7</name>
						<type>FieldName</type>
						<flags>
							<transparent>true</transparent>
							<xpStyle>false</xpStyle>
							<hasShadow>false</hasShadow>
							<toolbarButtonStyle>false</toolbarButtonStyle>
							<cache>false</cache>
							<hasBorder>false</hasBorder>
							<hasCheckbox>false</hasCheckbox>
						</flags>
					</general>
					<appearance>
						<index>37</index>
						<caption>Is faulty?</caption>
						<backgroundColor>#ffffff</backgroundColor>
						<foregroundColor>#000000</foregroundColor>
						<font  size="8">Arial</font>
						<alignment>Left</alignment>
						<borderStyle>None</borderStyle>
						<fillStyle>Solid</fillStyle>
					</appearance>
					<objectPlacement>
						<position>
							<top>166</top>
							<left>736</left>
							<right>788</right>
							<bottom>182</bottom>
						</position>
						<scaling>
							<top>0</top>
							<left>0</left>
							<right>0</right>
							<bottom>0</bottom>
						</scaling>
					</objectPlacement>
					<data>
						<binding>config_itemi.isfaulty</binding>
					</data>
					<controlInfo>
						<mouseOverCursor>Window Default</mouseOverCursor>
						<flags>
							<invisible>true</invisible>
							<skipTabStop>false</skipTabStop>
							<disabled>false</disabled>
							<protected>true</protected>
							<noMacroExpand>false</noMacroExpand>
							<multiLine>false</multiLine>
						</flags>
						<properties>
						</properties>
					</controlInfo>
				</control>
				<control>
					<general>
						<name>Field7</name>
						<type>Field</type>
					</general>
					<appearance>
						<index>38</index>
						<backgroundColor>#ffffff</backgroundColor>
						<foregroundColor>#000000</foregroundColor>
						<font  size="8">Arial</font>
						<borderStyle>3-D Sunken</borderStyle>
					</appearance>
					<objectPlacement>
						<position>
							<top>166</top>
							<left>788</left>
							<right>886</right>
							<bottom>182</bottom>
						</position>
						<scaling>
							<top>0</top>
							<left>0</left>
							<right>0</right>
							<bottom>0</bottom>
						</scaling>
					</objectPlacement>
					<data>
						<binding>config_itemi.isfaulty</binding>
					</data>
					<controlInfo>
						<mouseOverCursor>Window Default</mouseOverCursor>
						<type>Text Edit</type>
						<flags>
							<invisible>true</invisible>
							<readOnly>false</readOnly>
							<mandatory>false</mandatory>
							<mandatoryLabelBackground>false</mandatoryLabelBackground>
							<mandatoryLabelText>false</mandatoryLabelText>
							<allowNullValue>false</allowNullValue>
							<skipTabStop>false</skipTabStop>
							<disabled>false</disabled>
							<protected>true</protected>
							<noMacroExpand>false</noMacroExpand>
							<readOnlyInit>false</readOnlyInit>
							<autoCompleteField>false</autoCompleteField>
							<editUnlimitedText>false</editUnlimitedText>
							<url>false</url>
						</flags>
						<textLineCount>0</textLineCount>
						<textInputFormat>Text</textInputFormat>
						<properties>
							<content>#eeeeee</content>
							<disabledBackgroundColor>#eeeeee</disabledBackgroundColor>
						</properties>
					</controlInfo>
				</control>
				<control>
					<general>
						<name>Label8</name>
						<type>FieldName</type>
						<flags>
							<transparent>true</transparent>
							<xpStyle>false</xpStyle>
							<hasShadow>false</hasShadow>
							<toolbarButtonStyle>false</toolbarButtonStyle>
							<cache>false</cache>
							<hasBorder>false</hasBorder>
							<hasCheckbox>false</hasCheckbox>
						</flags>
					</general>
					<appearance>
						<index>39</index>
						<caption>Is unavailable?</caption>
						<backgroundColor>#ffffff</backgroundColor>
						<foregroundColor>#000000</foregroundColor>
						<font  size="8">Arial</font>
						<alignment>Left</alignment>
						<borderStyle>None</borderStyle>
						<fillStyle>Solid</fillStyle>
					</appearance>
					<objectPlacement>
						<position>
							<top>273</top>
							<left>732</left>
							<right>811</right>
							<bottom>289</bottom>
						</position>
						<scaling>
							<top>0</top>
							<left>0</left>
							<right>0</right>
							<bottom>0</bottom>
						</scaling>
					</objectPlacement>
					<data>
						<binding>config_itemi.isunavailable</binding>
					</data>
					<controlInfo>
						<mouseOverCursor>Window Default</mouseOverCursor>
						<flags>
							<invisible>true</invisible>
							<skipTabStop>false</skipTabStop>
							<disabled>false</disabled>
							<protected>true</protected>
							<noMacroExpand>false</noMacroExpand>
							<multiLine>false</multiLine>
						</flags>
						<properties>
						</properties>
					</controlInfo>
				</control>
				<control>
					<general>
						<name>Field8</name>
						<type>Field</type>
					</general>
					<appearance>
						<index>40</index>
						<backgroundColor>#ffffff</backgroundColor>
						<foregroundColor>#000000</foregroundColor>
						<font  size="8">Arial</font>
						<borderStyle>3-D Sunken</borderStyle>
					</appearance>
					<objectPlacement>
						<position>
							<top>273</top>
							<left>811</left>
							<right>832</right>
							<bottom>289</bottom>
						</position>
						<scaling>
							<top>0</top>
							<left>0</left>
							<right>0</right>
							<bottom>0</bottom>
						</scaling>
					</objectPlacement>
					<data>
						<binding>config_itemi.isunavailable</binding>
					</data>
					<controlInfo>
						<mouseOverCursor>Window Default</mouseOverCursor>
						<type>Text Edit</type>
						<flags>
							<invisible>true</invisible>
							<readOnly>false</readOnly>
							<mandatory>false</mandatory>
							<mandatoryLabelBackground>false</mandatoryLabelBackground>
							<mandatoryLabelText>false</mandatoryLabelText>
							<allowNullValue>false</allowNullValue>
							<skipTabStop>false</skipTabStop>
							<disabled>false</disabled>
							<protected>true</protected>
							<noMacroExpand>false</noMacroExpand>
							<readOnlyInit>false</readOnlyInit>
							<autoCompleteField>false</autoCompleteField>
							<editUnlimitedText>false</editUnlimitedText>
							<url>false</url>
						</flags>
						<textLineCount>0</textLineCount>
						<textInputFormat>Text</textInputFormat>
						<properties>
							<content>#eeeeee</content>
							<disabledBackgroundColor>#eeeeee</disabledBackgroundColor>
						</properties>
					</controlInfo>
				</control>
				<control>
					<general>
						<name>Label9</name>
						<type>FieldName</type>
						<flags>
							<transparent>true</transparent>
							<xpStyle>false</xpStyle>
							<hasShadow>false</hasShadow>
							<toolbarButtonStyle>false</toolbarButtonStyle>
							<cache>false</cache>
							<hasBorder>false</hasBorder>
							<hasCheckbox>false</hasCheckbox>
						</flags>
						<group>tabCom:0</group>
					</general>
					<appearance>
						<index>41</index>
						<caption>Organisation</caption>
						<backgroundColor>#ffffff</backgroundColor>
						<foregroundColor>#000000</foregroundColor>
						<font  size="8">Arial</font>
						<alignment>Right</alignment>
						<borderStyle>None</borderStyle>
						<fillStyle>Solid</fillStyle>
					</appearance>
					<objectPlacement>
						<position>
							<top>151</top>
							<left>329</left>
							<right>406</right>
							<bottom>169</bottom>
						</position>
						<scaling>
							<top>0</top>
							<left>50</left>
							<right>50</right>
							<bottom>0</bottom>
						</scaling>
					</objectPlacement>
					<data>
						<binding>config_itemi.companyname</binding>
					</data>
					<controlInfo>
						<mouseOverCursor>Window Default</mouseOverCursor>
						<properties>
						</properties>
					</controlInfo>
				</control>
				<control>
					<general>
						<name>tb_org_mult</name>
						<type>Field</type>
						<group>tabCom:0</group>
					</general>
					<appearance>
						<index>42</index>
						<backgroundColor>#ffffff</backgroundColor>
						<foregroundColor>#000000</foregroundColor>
						<font  size="8">Arial</font>
						<borderStyle>Rectangle</borderStyle>
					</appearance>
					<objectPlacement>
						<position>
							<top>151</top>
							<left>410</left>
							<right>605</right>
							<bottom>169</bottom>
						</position>
						<scaling>
							<top>0</top>
							<left>50</left>
							<right>100</right>
							<bottom>0</bottom>
						</scaling>
					</objectPlacement>
					<data>
					</data>
					<controlInfo>
						<mouseOverCursor>Window Default</mouseOverCursor>
						<type>Text Edit</type>
						<flags>
							<invisible>false</invisible>
							<readOnly>true</readOnly>
							<mandatory>false</mandatory>
							<mandatoryLabelBackground>false</mandatoryLabelBackground>
							<mandatoryLabelText>false</mandatoryLabelText>
							<allowNullValue>false</allowNullValue>
							<skipTabStop>false</skipTabStop>
							<disabled>false</disabled>
							<protected>false</protected>
							<noMacroExpand>false</noMacroExpand>
							<readOnlyInit>false</readOnlyInit>
							<autoCompleteField>false</autoCompleteField>
							<editUnlimitedText>false</editUnlimitedText>
							<url>false</url>
						</flags>
						<textLineCount>0</textLineCount>
						<textInputFormat>Text</textInputFormat>
						<properties>
							<borderColor>#000000</borderColor>
							<image>#eeeeee</image>
							<disabledBackgroundColor>#eeeeee</disabledBackgroundColor>
						</properties>
					</controlInfo>
				</control>
				<control>
					<general>
						<name>tb_contact_mult</name>
						<type>Field</type>
						<group>tabCom:0</group>
					</general>
					<appearance>
						<index>43</index>
						<backgroundColor>#ffffff</backgroundColor>
						<foregroundColor>#000000</foregroundColor>
						<font  size="8">Arial</font>
						<borderStyle>Rectangle</borderStyle>
					</appearance>
					<objectPlacement>
						<position>
							<top>195</top>
							<left>410</left>
							<right>605</right>
							<bottom>213</bottom>
						</position>
						<scaling>
							<top>0</top>
							<left>50</left>
							<right>100</right>
							<bottom>0</bottom>
						</scaling>
					</objectPlacement>
					<data>
					</data>
					<controlInfo>
						<mouseOverCursor>Window Default</mouseOverCursor>
						<type>Text Edit</type>
						<flags>
							<invisible>false</invisible>
							<readOnly>true</readOnly>
							<mandatory>false</mandatory>
							<mandatoryLabelBackground>false</mandatoryLabelBackground>
							<mandatoryLabelText>false</mandatoryLabelText>
							<allowNullValue>false</allowNullValue>
							<skipTabStop>false</skipTabStop>
							<disabled>false</disabled>
							<protected>false</protected>
							<noMacroExpand>false</noMacroExpand>
							<readOnlyInit>false</readOnlyInit>
							<autoCompleteField>false</autoCompleteField>
							<editUnlimitedText>false</editUnlimitedText>
							<url>false</url>
						</flags>
						<textLineCount>0</textLineCount>
						<textInputFormat>Text</textInputFormat>
						<properties>
							<borderColor>#000000</borderColor>
							<image>#eeeeee</image>
							<disabledBackgroundColor>#eeeeee</disabledBackgroundColor>
						</properties>
					</controlInfo>
				</control>
				<control>
					<general>
						<name>Label10</name>
						<type>FieldName</type>
						<flags>
							<transparent>true</transparent>
							<xpStyle>false</xpStyle>
							<hasShadow>false</hasShadow>
							<toolbarButtonStyle>false</toolbarButtonStyle>
							<cache>false</cache>
							<hasBorder>false</hasBorder>
							<hasCheckbox>false</hasCheckbox>
						</flags>
					</general>
					<appearance>
						<index>44</index>
						<caption>Category</caption>
						<backgroundColor>#ffffff</backgroundColor>
						<foregroundColor>#000000</foregroundColor>
						<font  size="8">Arial</font>
						<alignment>Left</alignment>
						<borderStyle>None</borderStyle>
						<fillStyle>Solid</fillStyle>
					</appearance>
					<objectPlacement>
						<position>
							<top>321</top>
							<left>772</left>
							<right>810</right>
							<bottom>337</bottom>
						</position>
						<scaling>
							<top>0</top>
							<left>0</left>
							<right>0</right>
							<bottom>0</bottom>
						</scaling>
					</objectPlacement>
					<data>
						<binding>config_itemi.fk_profilecode</binding>
					</data>
					<controlInfo>
						<mouseOverCursor>Window Default</mouseOverCursor>
						<flags>
							<invisible>true</invisible>
							<skipTabStop>false</skipTabStop>
							<disabled>false</disabled>
							<protected>false</protected>
							<noMacroExpand>false</noMacroExpand>
							<multiLine>false</multiLine>
						</flags>
						<properties>
						</properties>
					</controlInfo>
				</control>
				<control>
					<general>
						<name>Field3</name>
						<type>Field</type>
					</general>
					<appearance>
						<index>45</index>
						<backgroundColor>#ffffff</backgroundColor>
						<foregroundColor>#000000</foregroundColor>
						<font  size="8">Arial</font>
						<borderStyle>3-D Sunken</borderStyle>
					</appearance>
					<objectPlacement>
						<position>
							<top>320</top>
							<left>810</left>
							<right>917</right>
							<bottom>336</bottom>
						</position>
						<scaling>
							<top>0</top>
							<left>0</left>
							<right>0</right>
							<bottom>0</bottom>
						</scaling>
					</objectPlacement>
					<data>
						<binding>config_itemi.fk_profilecode</binding>
					</data>
					<controlInfo>
						<mouseOverCursor>Window Default</mouseOverCursor>
						<type>Text Edit</type>
						<flags>
							<invisible>true</invisible>
							<readOnly>false</readOnly>
							<mandatory>false</mandatory>
							<mandatoryLabelBackground>false</mandatoryLabelBackground>
							<mandatoryLabelText>false</mandatoryLabelText>
							<allowNullValue>false</allowNullValue>
							<skipTabStop>false</skipTabStop>
							<disabled>false</disabled>
							<protected>false</protected>
							<noMacroExpand>false</noMacroExpand>
							<readOnlyInit>false</readOnlyInit>
							<autoCompleteField>false</autoCompleteField>
							<editUnlimitedText>false</editUnlimitedText>
							<url>false</url>
						</flags>
						<textLineCount>0</textLineCount>
						<textInputFormat>Text</textInputFormat>
						<properties>
							<image>#eeeeee</image>
							<disabledBackgroundColor>#eeeeee</disabledBackgroundColor>
						</properties>
					</controlInfo>
				</control>
				<control>
					<general>
						<name>Field9</name>
						<type>Field</type>
					</general>
					<appearance>
						<index>46</index>
						<backgroundColor>#ffffff</backgroundColor>
						<foregroundColor>#000000</foregroundColor>
						<font  size="8">Arial</font>
						<borderStyle>3-D Sunken</borderStyle>
					</appearance>
					<objectPlacement>
						<position>
							<top>430</top>
							<left>340</left>
							<right>558</right>
							<bottom>446</bottom>
						</position>
						<scaling>
							<top>0</top>
							<left>0</left>
							<right>0</right>
							<bottom>0</bottom>
						</scaling>
					</objectPlacement>
					<data>
						<binding>config_itemi.companyname</binding>
					</data>
					<controlInfo>
						<mouseOverCursor>Window Default</mouseOverCursor>
						<type>Text Edit</type>
						<flags>
							<invisible>true</invisible>
							<readOnly>false</readOnly>
							<mandatory>false</mandatory>
							<mandatoryLabelBackground>false</mandatoryLabelBackground>
							<mandatoryLabelText>false</mandatoryLabelText>
							<allowNullValue>false</allowNullValue>
							<skipTabStop>false</skipTabStop>
							<disabled>false</disabled>
							<protected>false</protected>
							<noMacroExpand>false</noMacroExpand>
							<readOnlyInit>false</readOnlyInit>
							<autoCompleteField>false</autoCompleteField>
							<editUnlimitedText>false</editUnlimitedText>
							<url>false</url>
						</flags>
						<textLineCount>0</textLineCount>
						<textInputFormat>Text</textInputFormat>
						<properties>
							<imageHSpace>#eeeeee</imageHSpace>
							<disabledBackgroundColor>#eeeeee</disabledBackgroundColor>
						</properties>
					</controlInfo>
				</control>
			</controls>
			<formActions>
			</formActions>
			<javascript>
				<methods>
					<method>
						<name>OnFormLoaded</name>
						<code>
							<![CDATA[OnFormLoaded()
{
	_swdoc.SetTitle("Common Configuration Item Update");
		
	//-- setup field mode
	_swdoc.setup_form_fields();
	
	//-- reset modified flag	
	_swdoc.ResetModiedFlag("config_itemi");
}]]>
						</code>
					</method>
					<method>
						<name>lb_group_OnValueChanged</name>
						<code>
							<![CDATA[lb_group_OnValueChanged(strValue)
{
	_swdoc.oCI().ci_is_supported_by = "";
	app._ete(lb_analyst, "");
	_swdoc.UpdateFormFromData();
	
}]]>
						</code>
					</method>
					<method>
						<name>tb_type_OnLeftClick</name>
						<code>
							<![CDATA[tb_type_OnLeftClick()
{
	_swdoc.change_config_type(function()
	{
		return false;
	});
}]]>
						</code>
					</method>
					<method>
						<name>lb_cmdbstatus_OnValueChanged</name>
						<code>
							<![CDATA[lb_cmdbstatus_OnValueChanged(strValue)
{

}]]>
						</code>
					</method>
					<method>
						<name>lb_status_OnValueChanged</name>
						<code>
							<![CDATA[lb_status_OnValueChanged(strValue)
{

	_swdoc.oCI().isfaulty = "No";
	_swdoc.oCI().isdeactivated = "No";
	_swdoc.oCI().isactive = "No";		
	_swdoc.oCI().isunavailable = "No";	
				
	//-- check if selected status is an unavailable status or inactive
	var strStatus = app.cmdb.get_cmdbstatus(_swdoc.oCI().ck_config_type, strValue);
	_swdoc.oCI().cmdb_status = strStatus;
	
	if (strStatus.toLowerCase()=="unavailable")
	{
		_swdoc.oCI().isunavailable = "Yes";
	}
	else if (strStatus.toLowerCase()=="deactivated")
	{
		_swdoc.oCI().isdeactivated = "Yes"
	}
	else if (strStatus.toLowerCase()=="faulty")
	{
		_swdoc.oCI().isfaulty = "Yes";		
	}
	else 
	{
		//-- assume active
		_swdoc.oCI().isactive = "Yes";				
	}
	
	_swdoc.UpdateFormFromData();	
}]]>
						</code>
					</method>
					<method>
						<name>flg_authorised_OnValueChanged</name>
						<code>
							<![CDATA[flg_authorised_OnValueChanged(strValue)
{
	_swdoc.oCI().isauthorised = (strValue==0)?"No":"Yes";
	_swdoc.UpdateFormFromData();
	
}]]>
						</code>
					</method>
					<method>
						<name>lb_profile_OnLeftClick</name>
						<code>
							<![CDATA[lb_profile_OnLeftClick()
{
	
	//--
	app.g.pick_problemprofile("","",true, function(strInfo){
		if(strInfo!=""){
		  _swdoc.oCI().fk_profilecode = strInfo.split("|")[0];
		  app._ete(lb_profile, strInfo.split("|")[1]);
		  _swdoc.UpdateFormFromData();
		}
	
	});

	return false;
}]]>
						</code>
					</method>
					<method>
						<name>lb_profile_OnRightClick</name>
						<code>
							<![CDATA[lb_profile_OnRightClick()
{
		_swdoc.oCI().fk_profilecode = "";
		app._ete(lb_profile, "");
		_swdoc.UpdateFormFromData();
}]]>
						</code>
					</method>
					<method>
						<name>lb_company_OnValueChanged</name>
						<code>
							<![CDATA[lb_company_OnValueChanged(strValue)
{

	var strFilter = "_swc_fk_company_id=" + app.pfu(strValue);
	app._slf(lb_site , strFilter);
	app._slf(lb_contact , strFilter);

	_swdoc.oCI().companyname = lb_company.display;
	app._evi(tb_org_mult, false);
	
	_swdoc.oCI().fk_site = "";
	_swdoc.oCI().fk_userdb = "";	
	_swdoc.oCI().owner_name = "";
	app._evi(tb_contact_mult, false);
	
	_swdoc.UpdateFormFromData();

}]]>
						</code>
					</method>
					<method>
						<name>lb_contact_OnValueChanged</name>
						<code>
							<![CDATA[lb_contact_OnValueChanged(strValue)
{

	_swdoc.oCI().owner_name = lb_contact.text;
	app._evi(tb_contact_mult, false);	


}]]>
						</code>
					</method>
				</methods>
			</javascript>
		</layout>
		<layout>
			<appearance>
				<width>360</width>
				<height>220</height>
				<backgroundColor>#ffffff</backgroundColor>
				<fillColour>#ffffff</fillColour>
				<textColour >#000000</textColour >
				<font  size="8">Arial</font>
			</appearance>
			<controls>
			</controls>
			<formActions>
			</formActions>
			<javascript>
				<methods>
				</methods>
			</javascript>
		</layout>
	</layouts>
</espForm>
