<Config>
	<TrustedAuthentication>
		<secretKey value="dgvzda=="/>
		<authorisedIpAddressNumber value="1"/>
		<authorisedIpAddress1 value="127.0.0.1"/>
	</TrustedAuthentication>
	<FormsDirectory value="C:\Program Files (x86)\Hornbill\Supportworks Server\forms"/>
	<OrganisationName value=""/>
	<Site id="" name="" contact="" tel=""/>
	<InstallPath value="C:\Program Files (x86)\Hornbill\Supportworks Server"/>
	<Version value="8.2.0"/>
	<CS>
		<InstallPath value="c:\Program Files (x86)\Hornbill\Core Services\"/>
		<Version value="6.0.0"/>
	</CS>
	<Addins>
		<Authentication>
			<ADS>
				<Driver value="C:\Program Files (x86)\Hornbill\Supportworks Server\bin\swadauth.dll"/>
				<DisplayName value="Windows 2000 Active Directory"/>
				<AuthStringName value="User Principle Name"/>
			</ADS>
			<LDA>
				<Driver value="C:\Program Files (x86)\Hornbill\Supportworks Server\bin\swldapauth.dll"/>
				<DisplayName value="LDAP"/>
				<AuthStringName value="LDAP Server/DN"/>
			</LDA>
			<NDS>
				<Driver value="C:\Program Files (x86)\Hornbill\Supportworks Server\bin\swnwauth.dll"/>
				<DisplayName value="Novell NDS"/>
				<AuthStringName value="Novell NDS User"/>
			</NDS>
			<NTD>
				<Driver value="C:\Program Files (x86)\Hornbill\Supportworks Server\bin\swntauth.dll"/>
				<DisplayName value="NT Domain"/>
				<AuthStringName value="NT Domain\User ID"/>
			</NTD>
		</Authentication>
		<Inventory>
			<DisplayName value="Supportworks PC Audit"/>
			<Driver value=""/>
		</Inventory>
	</Addins>
	<AutoMaster>
		<DataCollectionPoint value="C:\Program Files (x86)\Hornbill\Supportworks Server\automast"/>
		<DefaultDeliveryGroup value="SUPPORT"/>
		<PollInterval value="25"/>
		<IdleState value="17"/>
		<IdlePass value="16"/>
		<ScheduledEventPass value="2"/>
		<IdleLastLoopTime value="15/07/2003 22:32:09"/>
		<DefaultPriority value="2 Hours Response"/>
		<EnableAutomaster value="1"/>
	</AutoMaster>
	<Communications>
		<EnableXMLMCDocumentation value="1"/>
		<AllowMultiLogin value="1"/>
		<DisableLogin value="0"/>
		<HTTPServicePort value="80"/>
		<ServicePort value="5001"/>
		<AllowDenyMode value="0"/>
		<IdleTimeout value="8"/>
		<UseAsyncNPA value="1"/>
		<UseThreadPerSession value="1"/>
		<AccessRules mode="allowallexcept"/>
		<Options value="52"/>
		<HelpdeskApiThreadPoolCount value="25"/>
		<MaxUploadFileSize value="10000000"/>
		<ConnectionTimeOutSecs value="60"/>
		<HelpdeskApiThreadPoolCount value="24"/>
		<SendSupportInfoToHornbill value="1"/>
		<DisableMultiLogin value="0"/>
		<MultiLoginOption value="0"/>
		<CloseMessengerOption value="0"/>
	</Communications>
	<Database>
		<CacheDirectory value="C:\Program Files (x86)\Hornbill\Supportworks Server\cache"/>
		<DataDirectory value="C:\Program Files (x86)\Hornbill\Supportworks Server\data"/>
		<CFAStore value="C:\Program Files (x86)\Hornbill\Supportworks Server\data\cfa_store"/>
		<DefaultDSN value="Supportworks Data"/>
		<DefaultPWD value="m1Q+4qo4PilMcmYkwYsQmWk9k5d9Splm7Pkm9eI2xeOmtDGLTd0=" encrypt="1"/>
		<DefaultUID value="root"/>
		<DumpDirectory value="C:\Program Files (x86)\Hornbill\Supportworks Server\dump"/>
		<DumpDirectoryMinSpaceThreshold value="100"/>
		<StatusCheckDelay value="20"/>
		<OdbcConnectPoolCount value="4"/>
		<OdbcConnectPoolMax value="16"/>
		<AutoCloseResolvedCalls value="0"/>
		<AutoCloseResolvedCallsDays value="60"/>
		<DailyIncremental value="1"/>
		<LogStatsSqlUpdates value="1"/>
		<DailyStatKeepCount value="90"/>
		<WeeklyStatKeepCount value="180"/>
		<MonthlyStatKeepCount value="360"/>
		<DailyTotalsKeepCount value="90"/>
		<RecordDailyStats value="1"/>
		<RecordWeeklyStats value="1"/>
		<RecordMonthlyStats value="1"/>
		<RecordTotalsStats value="1"/>
		<CachePoolCount value="64"/>
		<CachePoolMaxRetry value="5"/>
		<CachePoolWaitForConnection value="100"/>
		<SwSqlGlobalRootAccountMsl value="root"/>
		<SwSqlGlobalRootPasswordMsl value="4yuMctdPqZUHoT9pSoP5NWyDdaRAFwoCGu0BVbQHKtcj/3SQSfc=" encrypt="1"/>
		<StoredQuerySecured value="0"/>
		<StoredQueryPort value="80"/>
		<StoredQueryUseChilkat value="1"/>
		<StoredQueryLogging value="C:\Program Files (x86)\Hornbill\Supportworks Server\log\storedquery.log"/>
		<Tables/>
	</Database>
	<Datamanager>
		<SqlScripts value="C:\Program Files (x86)\Hornbill\Supportworks Server\sql"/>
	</Datamanager>
	<EmailCallLogging>
		<AssignAnalyst value=""/>
		<AssignGroup value="SUPPORT"/>
		<ProblemProfileCode value="OTHR-OTHR-OTHR"/>
		<ServiceLevelAgreement value="&lt;Use Customer's SLA&gt;"/>
		<LogFileMaxDaysOld value="7"/>
	</EmailCallLogging>
	<Feedback>
		<Disable value="0"/>
	</Feedback>
	<FileService>
		<Port value="5021"/>
		<MaxFileSize value="10000000"/>
		<Lock value="1"/>
		<RootFolder value="C:\Program Files (x86)\Hornbill\Supportworks Server\data"/>
		<SystemLibraryResources>
			<Resource name="System Administration/Log Files" path="C:\Program Files (x86)\Hornbill\Supportworks Server/log" rights="4294967295"/>
			<Resource name="System Administration/Archived Log Files" path="C:\Program Files (x86)\Hornbill\Supportworks Server/logarchive" rights="4294967295"/>
			<Resource name="System Administration/Data Dictionaries" path="C:\Program Files (x86)\Hornbill\Supportworks Server/data/_dd_data" rights="4294967295"/>
			<Resource name="System Administration/Server-Side Scripts" path="C:\Program Files (x86)\Hornbill\Supportworks Server/scripts" rights="4294967295"/>
			<Resource name="System Administration/KnowledgeBase Document Folder" path="C:\Program Files (x86)\Hornbill\Supportworks Server/KnowledgeBase" rights="4294967295"/>
			<Resource name="System Administration/AutoMaster Drop Folder" path="C:\Program Files (x86)\Hornbill\Supportworks Server/automast" rights="4294967295"/>
		</SystemLibraryResources>
	</FileService>
	<KnowledgeBase>
		<KnowledgeBaseIndexDirectory value="C:\Program Files (x86)\Hornbill\Supportworks Server\KnowledgeBase"/>
		<DocAuthor value=""/>
		<DocAuthorUseAnalyst value="1"/>
		<KnowledgeBaseEnabled value="1"/>
		<DocCatagory value="Supportworks Helpdesk Incident"/>
		<KnowledgebaseTemplateFile value="C:\Program Files (x86)\Hornbill\Supportworks Server\postbox\template\ClosesCallKnowledgePage.htm.template"/>
		<UseHtmlKnowledgeTemplate value="1"/>
		<KnowledgeBaseReferenceFormat value="KB%Y%m&amp;mi"/>
		<KnowledgeBaseTemplateFileNew value="C:\Program Files (x86)\Hornbill\Supportworks Server\postbox\template\kbdoctemplate.htm"/>
	</KnowledgeBase>
	<DataDictionaryExport>
		<Verbose value="0"/>
		<LogExport value="0"/>
	</DataDictionaryExport>
	<Logging>
		<ArchiveCommandLine value="COPY %in %outdir\%date-%time-%inc.log"/>
		<ArchiveDirectory value="C:\Program Files (x86)\Hornbill\Supportworks Server\logarchive"/>
		<ArchiveIncremental value="1396"/>
		<ArchiveOnClear value="1"/>
		<ArchiveLogTime value="23:45"/>
		<ClearLogOnStartup value="1"/>
		<EnableLogging value="1"/>
		<LogFileMaxDaysOld value="7"/>
		<LogFileName value="C:\Program Files (x86)\Hornbill\Supportworks Server\log\swserver.log"/>
		<LogComms value="1"/>
		<LogDatabase value="1"/>
		<LogMail value="1"/>
		<LogProcess value="0"/>
		<LogSecurity value="1"/>
		<LogSQL value="1"/>
		<LogSystem value="1"/>
		<LogVpme value="1"/>
		<ResetLogDaily value="1"/>
		<TypeDebug value="0"/>
		<TypeErrors value="1"/>
		<TypeWarnings value="1"/>
		<TypeInformation value="1"/>
		<BeepOnError value="0"/>
	</Logging>
	<Messaging>
		<AllowGALDownload value="1"/>
		<DeliveryDirectory value="C:\Program Files (x86)\Hornbill\Supportworks Server\postbox\delivery"/>
		<DeliveryRetries value="5"/>
		<GALRebuildTime value="5:00"/>
		<MailRouterPollIntervall value="15"/>
		<LearnNewAddresses value="1"/>
		<MailTemplateDirectory value="C:\Program Files (x86)\Hornbill\Supportworks Server\postbox\template"/>
		<TemplateDirectory value="C:\Program Files (x86)\Hornbill\Supportworks Server\postbox\template"/>
		<PostBoxDirectory value="C:\Program Files (x86)\Hornbill\Supportworks Server\postbox"/>
		<WelcomeFileName value="C:\Program Files (x86)\Hornbill\Supportworks Server\postbox\welcome.txt"/>
		<BuildGAL value="1"/>
		<SMTPServerPort value="25"/>
		<EnableSMTPServer value="1"/>
		<SMTPServerTrackingEnabled value="0"/>
		<SMTPServerTrackingPath value=""/>
		<SMTPServerAllowVrfyCommand value="0"/>
		<SMTPServerAllowDirectMbRouting value="1"/>
		<SMTPMaximumInboundMessageSize value="0"/>
		<ImportFromCustomerDatabase value="1"/>
		<DefaultSharedMailbox value="_helpdesk"/>
		<SocketTimeOut value="60"/>
		<InsertPersonalAddressesIntoGAL value="1"/>
		<InsertSharedAddressesIntoGAL value="1"/>
		<MaxUploadFileSize value="10000000"/>
		<ConnectionTimeOutSecs value="10"/>
		<InitFolderUnreadCounts value="0"/>
		<RoutingRules enable="yes">
			<rule>
				<condition>subject LIKE &apos;?%&apos;</condition>
				<mailbox>_helpdesk</mailbox>
				<folder>Inbox</folder>
				<mode>AutoResponder</mode>
			</rule>
			<rule>
				<condition>SUBJECT LIKE &apos;AWS Request Authorization Decision%&apos;</condition>
				<mailbox/>
				<folder/>
				<mode>AutoResponder</mode>
			</rule>
		</RoutingRules>
	</Messaging>
	<Reports>
		<HttpReportQueryTool value="C:\Program Files (x86)\Hornbill\Supportworks Server\bin\swhttpget.exe"/>
		<EventEngine value="C:\Program Files (x86)\Hornbill\Supportworks Server\bin\swrptevt.exe"/>
		<QueryEngine value="C:\Program Files (x86)\Hornbill\Supportworks Server\bin\swrptqry.exe"/>
		<ReportDirectory value="C:\Program Files (x86)\Hornbill\Supportworks Server\legacy_reports"/>
		<ReportImportUpgrade value="0"/>
		<ScheduledReportTimeoutSeconds value="20"/>
	</Reports>
	<Schedule>
		<ScheduleDirectory value="C:\Program Files (x86)\Hornbill\Supportworks Server\Schedule"/>
	</Schedule>
	<Scripting>
		<ScriptCommand value="&quot;&quot; -q %s"/>
		<ScriptEnable value="1"/>
		<ScriptPath value="C:\Program Files (x86)\Hornbill\Supportworks Server\scripts"/>
		<ScriptPriority value="0"/>
		<ScriptTimeout value="300"/>
		<DebugPort value="0"/>
		<ScriptMode value="2"/>
		<WebServerBaseUrl value="http://127.0.0.1/sw/sss"/>
	</Scripting>
	<ServerRegionalSettings>
		<TimeZone value="GMT Standard Time"/>
		<DateTimeFormat value="dd/MM/yyyy HH:mm:ss"/>
		<DateFormat value="dd/MM/yyyy"/>
		<TimeFormat value="HH:mm:ss"/>
		<CurrencySymbol value="£"/>
		<Country value="2057"/>
	</ServerRegionalSettings>
	<DefaultWorkingTime>
		<Timezone value="GMT Standard Time"/>
		<Sunday start="00:00" end="00:00"/>
		<Monday start="09:00" end="17:00"/>
		<Tuesday start="09:00" end="17:00"/>
		<Wednesday start="09:00" end="17:00"/>
		<Thursday start="09:00" end="17:00"/>
		<Friday start="09:00" end="17:00"/>
		<Saturday start="00:00" end="00:00"/>
		<Exclusions>
			<Exclusion name="Christmas Day" day="25" month="12"/>
			<Exclusion name="Boxing Day" day="26" month="12"/>
			<Exclusion name="New Years Day" day="1" month="1"/>
		</Exclusions>
		<DefaultSLA value="[Use Customer's SLA]"/>
	</DefaultWorkingTime>
	<VPME>
		<RootPath value="C:\Program Files (x86)\Hornbill\Supportworks Server\vpme"/>
		<EnableLogFile value="1"/>
		<LogEmptyVariables value="0"/>
		<EnableAppEvents value="1"/>
		<EnableTableEvents value="1"/>
		<EnableScheduledEvents value="1"/>
		<EnableGenericScriptExecution value="1"/>
		<VPMEQueryMaxRecords value="5000"/>
	</VPME>
	<RunOnce>
		<DD name="Default">
			<AddDefaultWatchedCallsSettingsToDataDictionary value="0"/>
			<CleanDateFormat value="0"/>
			<UpgradeQuickCalls value="0"/>
			<AddDefaultDataSourceToPickList value="0"/>
			<UpdateLegacyDTColumnsInSearchForCallsView value="0"/>
			<ReorganizeGlobalParameters value="0"/>
			<AddDefaultMobileViews value="0" type="dword"/>
			<InitialiseAnalystAppRightsTable type="dword" value="0"/>
		</DD>
		<AddDefRegionalSettings type="dword" value="0"/>
		<UpdateWebSelfServiceSettings type="dword" value="0"/>
		<DD name="ITSM_DEFAULT">
			<AddDefaultDataSourceToPickList type="dword" value="0"/>
			<AddDefaultWatchedCallsSettingsToDataDictionary type="dword" value="0"/>
			<CleanDateFormat type="dword" value="0"/>
			<RemoveLegacyTimeSpent type="dword" value="0"/>
			<UpgradeQuickCalls type="dword" value="0"/>
			<UpdateLegacyDTColumnsInSearchForCallsView type="dword" value="0"/>
			<InitialiseAnalystAppRightsTable type="dword" value="0"/>
			<AddDefaultMobileViews type="dword" value="0"/>
		</DD>
		<UpdateSurveyResultsTable type="dword" value="0"/>
		<DD name="ITSM">
			<AddDefaultDataSourceToPickList type="dword" value="0"/>
			<AddDefaultWatchedCallsSettingsToDataDictionary type="dword" value="0"/>
			<CleanDateFormat type="dword" value="0"/>
			<RemoveLegacyTimeSpent type="dword" value="0"/>
			<UpgradeQuickCalls type="dword" value="0"/>
			<UpdateLegacyDTColumnsInSearchForCallsView type="dword" value="0"/>
			<InitialiseAnalystAppRightsTable type="dword" value="0"/>
			<AddDefaultMobileViews type="dword" value="0"/>
		</DD>
		<DD name="TESTDESIGN">
			<AddDefaultDataSourceToPickList type="dword" value="0"/>
			<AddDefaultWatchedCallsSettingsToDataDictionary type="dword" value="0"/>
			<CleanDateFormat type="dword" value="0"/>
			<RemoveLegacyTimeSpent type="dword" value="0"/>
			<UpgradeQuickCalls type="dword" value="0"/>
			<UpdateLegacyDTColumnsInSearchForCallsView type="dword" value="0"/>
			<InitialiseAnalystAppRightsTable type="dword" value="0"/>
			<AddDefaultMobileViews type="dword" value="0"/>
		</DD>
		<DD name="ITSM - COPY">
			<AddDefaultDataSourceToPickList type="dword" value="0"/>
			<AddDefaultWatchedCallsSettingsToDataDictionary type="dword" value="0"/>
			<CleanDateFormat type="dword" value="0"/>
			<RemoveLegacyTimeSpent type="dword" value="0"/>
			<UpgradeQuickCalls type="dword" value="0"/>
			<UpdateLegacyDTColumnsInSearchForCallsView type="dword" value="0"/>
			<InitialiseAnalystAppRightsTable type="dword" value="0"/>
			<AddDefaultMobileViews type="dword" value="0"/>
		</DD>
		<DD name="DEVITSM">
			<AddDefaultDataSourceToPickList type="dword" value="0"/>
			<AddDefaultWatchedCallsSettingsToDataDictionary type="dword" value="0"/>
			<CleanDateFormat type="dword" value="0"/>
			<RemoveLegacyTimeSpent type="dword" value="0"/>
			<UpgradeQuickCalls type="dword" value="0"/>
			<UpdateLegacyDTColumnsInSearchForCallsView type="dword" value="0"/>
			<InitialiseAnalystAppRightsTable type="dword" value="0"/>
			<AddDefaultMobileViews type="dword" value="0"/>
		</DD>
		<DD name="ARCH">
			<AddDefaultDataSourceToPickList type="dword" value="0"/>
			<AddDefaultWatchedCallsSettingsToDataDictionary type="dword" value="0"/>
			<CleanDateFormat type="dword" value="0"/>
			<RemoveLegacyTimeSpent type="dword" value="0"/>
			<UpgradeQuickCalls type="dword" value="0"/>
			<UpdateLegacyDTColumnsInSearchForCallsView type="dword" value="0"/>
			<InitialiseAnalystAppRightsTable type="dword" value="0"/>
			<AddDefaultMobileViews type="dword" value="0"/>
		</DD>
		<DD name="TESTING123">
			<AddDefaultDataSourceToPickList type="dword" value="0"/>
			<AddDefaultWatchedCallsSettingsToDataDictionary type="dword" value="0"/>
			<CleanDateFormat type="dword" value="0"/>
			<RemoveLegacyTimeSpent type="dword" value="0"/>
			<UpgradeQuickCalls type="dword" value="0"/>
			<UpdateLegacyDTColumnsInSearchForCallsView type="dword" value="0"/>
			<InitialiseAnalystAppRightsTable type="dword" value="0"/>
			<AddDefaultMobileViews type="dword" value="0"/>
		</DD>
		<DD name="REDESIGN_ITSM">
			<AddDefaultDataSourceToPickList type="dword" value="0"/>
			<AddDefaultWatchedCallsSettingsToDataDictionary type="dword" value="0"/>
			<CleanDateFormat type="dword" value="0"/>
			<RemoveLegacyTimeSpent type="dword" value="0"/>
			<UpgradeQuickCalls type="dword" value="0"/>
			<UpdateLegacyDTColumnsInSearchForCallsView type="dword" value="0"/>
			<InitialiseAnalystAppRightsTable type="dword" value="0"/>
			<AddDefaultMobileViews type="dword" value="0"/>
		</DD>
		<DD name="ITSM_PSPM_V5">
			<AddDefaultDataSourceToPickList type="dword" value="0"/>
			<AddDefaultWatchedCallsSettingsToDataDictionary type="dword" value="0"/>
			<CleanDateFormat type="dword" value="0"/>
			<RemoveLegacyTimeSpent type="dword" value="0"/>
			<UpgradeQuickCalls type="dword" value="0"/>
			<UpdateLegacyDTColumnsInSearchForCallsView type="dword" value="0"/>
			<InitialiseAnalystAppRightsTable type="dword" value="0"/>
			<AddDefaultMobileViews type="dword" value="0"/>
		</DD>
	</RunOnce>
	<AutoResponder>
		<rules>
			<rule>
				<name>Log New Call</name>
				<condition>TOKEN(subject, 0, 1) IN(&apos;LogCall&apos;,&apos;LogNewCall&apos;)</condition>
				<application>Default</application>
				<callClass>Incident</callClass>
				<profileCode>OTHR</profileCode>
				<assignGroup>SUPPORT</assignGroup>
				<defaultSla>[Use Customer&apos;s SLA]</defaultSla>
				<replyMailbox>_helpdesk</replyMailbox>
				<replyTemplateOk>Log Call Request Accepted</replyTemplateOk>
				<replyTemplateFail>Log Call Request Rejected</replyTemplateFail>
				<serviceControlTable>userdb</serviceControlTable>
				<serviceControlTableKey>keysearch</serviceControlTableKey>
				<serviceControlTableMatchColumn>email</serviceControlTableMatchColumn>
				<serviceControlTableControl>webflag</serviceControlTableControl>
				<serviceControlTableControlBit>9</serviceControlTableControlBit>
				<serviceControlMatchWith>fromAddress</serviceControlMatchWith>
				<vpmeScriptNameOk name="arLogNewCall" includeFiles="1">
					<params>
						<customerId>sc_keysearch</customerId>
						<customerFirstname>sc_firstname</customerFirstname>
						<customerLastname>sc_surname</customerLastname>
						<callClass>callClass</callClass>
						<assignGroup>assignGroup</assignGroup>
						<profileCode>profileCode</profileCode>
						<replyEmail>fromAddress</replyEmail>
						<replyMailbox>mailbox</replyMailbox>
						<replyTemplateOk>replyTemplateOk</replyTemplateOk>
						<replyTemplateFail>replyTemplateFail</replyTemplateFail>
						<msgSubject>subject</msgSubject>
						<msgBody>body</msgBody>
						<sla>sc_priority</sla>
						<originalEmailID>originalEmail</originalEmailID>
						<boolAttachEmail>1</boolAttachEmail>
					</params>
				</vpmeScriptNameOk>
				<vpmeScriptNameFail name="arRequestFail" includeFiles="1">
					<params>
						<replyEmail>fromAddress</replyEmail>
						<replyMailbox>mailbox</replyMailbox>
						<replyTemplateFail>replyTemplateFail</replyTemplateFail>
						<errorMessage>errorMessage</errorMessage>
					</params>
				</vpmeScriptNameFail>
				<serviceControlEnable>yes</serviceControlEnable>
			</rule>
			<rule>
				<name>Update Call</name>
				<serviceControlMatchWith>fromAddress</serviceControlMatchWith>
				<serviceControlTable>userdb</serviceControlTable>
				<replyMailbox>_helpdesk</replyMailbox>
				<condition>TOKEN(subject, 0, 1) = &apos;UpdateCall&apos;</condition>
				<application>Default</application>
				<callClass>Incident</callClass>
				<assignGroup>SUPPORT</assignGroup>
				<defaultSla>2 Hours Response</defaultSla>
				<serviceControlTableKey>keysearch</serviceControlTableKey>
				<serviceControlTableMatchColumn>email</serviceControlTableMatchColumn>
				<serviceControlTableControl>webflag</serviceControlTableControl>
				<serviceControlTableControlBit>10</serviceControlTableControlBit>
				<replyTemplateOk>Confirmation of Call Update</replyTemplateOk>
				<replyTemplateFail>Call Update Request Rejected</replyTemplateFail>
				<vpmeScriptNameOk name="arUpdateCall" includeFiles="1">
					<params>
						<callRef>CALLREF_VALUE(subject)</callRef>
						<customerId>sc_keysearch</customerId>
						<customerFirstname>sc_firstname</customerFirstname>
						<customerLastname>sc_surname</customerLastname>
						<replyEmail>fromAddress</replyEmail>
						<replyMailbox>mailbox</replyMailbox>
						<replyTemplateOk>replyTemplateOk</replyTemplateOk>
						<replyTemplateFail>replyTemplateFail</replyTemplateFail>
						<msgSubject>subject</msgSubject>
						<msgBody>body</msgBody>
						<originalEmailID>originalEmail</originalEmailID>
						<boolAttachEmail>1</boolAttachEmail>
					</params>
				</vpmeScriptNameOk>
				<vpmeScriptNameFail name="arRequestFail" includeFiles="0">
					<params>
						<replyEmail>fromAddress</replyEmail>
						<replyMailbox>mailbox</replyMailbox>
						<replyTemplateFail>replyTemplateFail</replyTemplateFail>
						<errorMessage>errorMessage</errorMessage>
					</params>
				</vpmeScriptNameFail>
				<serviceControlEnable>yes</serviceControlEnable>
			</rule>
			<rule>
				<name>SelfService Password Reminder</name>
				<serviceControlMatchWith>fromAddress</serviceControlMatchWith>
				<serviceControlTable>userdb</serviceControlTable>
				<replyMailbox>_helpdesk</replyMailbox>
				<condition>TOKEN(subject, 0, 1) IN (&apos;WebPassword&apos;, &apos;WebPasswordQuery&apos;)</condition>
				<application>Default</application>
				<callClass>Incident</callClass>
				<assignGroup>SUPPORT</assignGroup>
				<defaultSla>2 Hours Response</defaultSla>
				<serviceControlTableKey>keysearch</serviceControlTableKey>
				<serviceControlTableMatchColumn>email</serviceControlTableMatchColumn>
				<serviceControlTableControl>webflag</serviceControlTableControl>
				<serviceControlTableControlBit>0</serviceControlTableControlBit>
				<replyTemplateOk>Web Password Request</replyTemplateOk>
				<replyTemplateFail>Web Password Request Rejected</replyTemplateFail>
				<vpmeScriptNameOk name="arSelfServicePasswordRequest" includeFiles="0">
					<params>
						<customerId>sc_keysearch</customerId>
						<customerFirstname>sc_firstname</customerFirstname>
						<customerLastname>sc_surname</customerLastname>
						<selfServicePassword>sc_password</selfServicePassword>
						<replyEmail>fromAddress</replyEmail>
						<replyMailbox>mailbox</replyMailbox>
						<replyTemplateOk>replyTemplateOk</replyTemplateOk>
						<replyTemplateFail>replyTemplateFail</replyTemplateFail>
						<msgSubject>subject</msgSubject>
						<msgBody>body</msgBody>
					</params>
				</vpmeScriptNameOk>
				<vpmeScriptNameFail name="arRequestFail" includeFiles="0">
					<params>
						<replyEmail>fromAddress</replyEmail>
						<replyMailbox>mailbox</replyMailbox>
						<replyTemplateFail>replyTemplateFail</replyTemplateFail>
						<errorMessage>errorMessage</errorMessage>
					</params>
				</vpmeScriptNameFail>
				<serviceControlEnable>yes</serviceControlEnable>
			</rule>
			<rule>
				<name>Open Calls List</name>
				<serviceControlMatchWith>fromAddress</serviceControlMatchWith>
				<serviceControlTable>userdb</serviceControlTable>
				<replyMailbox>_helpdesk</replyMailbox>
				<condition>TOKEN(subject, 0, 1) IN (&apos;OpenCalls&apos;, &apos;OpenCallSummaryRequest&apos;)</condition>
				<application>Default</application>
				<callClass>Incident</callClass>
				<assignGroup>SUPPORT</assignGroup>
				<defaultSla>2 Hours Response</defaultSla>
				<serviceControlTableKey>keysearch</serviceControlTableKey>
				<serviceControlTableMatchColumn>email</serviceControlTableMatchColumn>
				<serviceControlTableControl>webflag</serviceControlTableControl>
				<serviceControlTableControlBit>8</serviceControlTableControlBit>
				<replyTemplateOk>Open Calls Summary Request</replyTemplateOk>
				<replyTemplateFail>No Open Calls Summary Request</replyTemplateFail>
				<vpmeScriptNameOk name="arOpenCallSummaryReport" includeFiles="0">
					<params>
						<customerId>sc_keysearch</customerId>
						<customerFirstname>sc_firstname</customerFirstname>
						<customerLastname>sc_surname</customerLastname>
						<replyEmail>fromAddress</replyEmail>
						<replyMailbox>mailbox</replyMailbox>
						<replyTemplateOk>replyTemplateOk</replyTemplateOk>
						<replyTemplateFail>replyTemplateFail</replyTemplateFail>
						<msgSubject>subject</msgSubject>
					</params>
				</vpmeScriptNameOk>
				<vpmeScriptNameFail name="arRequestFail" includeFiles="1">
					<params>
						<replyEmail>fromAddress</replyEmail>
						<replyMailbox>mailbox</replyMailbox>
						<replyTemplateFail>replyTemplateFail</replyTemplateFail>
						<errorMessage>errorMessage</errorMessage>
					</params>
				</vpmeScriptNameFail>
				<serviceControlEnable>yes</serviceControlEnable>
			</rule>
			<rule>
				<name>Call Status Request</name>
				<serviceControlMatchWith>fromAddress</serviceControlMatchWith>
				<serviceControlTable>userdb</serviceControlTable>
				<replyMailbox>_helpdesk</replyMailbox>
				<condition>TOKEN(subject, 0, 1) IN (&apos;CallStatus&apos;, &apos;CallStatusRequest&apos;)</condition>
				<application>Default</application>
				<callClass>Incident</callClass>
				<assignGroup>SUPPORT</assignGroup>
				<defaultSla>2 Hours Response</defaultSla>
				<serviceControlTableKey>keysearch</serviceControlTableKey>
				<serviceControlTableMatchColumn>email</serviceControlTableMatchColumn>
				<serviceControlTableControl>webflag</serviceControlTableControl>
				<serviceControlTableControlBit>8</serviceControlTableControlBit>
				<replyTemplateOk>Call Status Request</replyTemplateOk>
				<replyTemplateFail>Mailback Request Rejected</replyTemplateFail>
				<vpmeScriptNameOk name="arCallStatusRequest" includeFiles="0">
					<params>
						<callRef>CALLREF_VALUE(subject)</callRef>
						<customerId>sc_keysearch</customerId>
						<customerFirstname>sc_firstname</customerFirstname>
						<customerLastname>sc_surname</customerLastname>
						<replyEmail>fromAddress</replyEmail>
						<replyMailbox>mailbox</replyMailbox>
						<replyTemplateOk>replyTemplateOk</replyTemplateOk>
						<replyTemplateFail>replyTemplateFail</replyTemplateFail>
						<msgSubject>subject</msgSubject>
					</params>
				</vpmeScriptNameOk>
				<vpmeScriptNameFail name="arRequestFail" includeFiles="true">
					<params>
						<replyEmail>fromAddress</replyEmail>
						<replyMailbox>mailbox</replyMailbox>
						<replyTemplateFail>replyTemplateFail</replyTemplateFail>
						<errorMessage>errorMessage</errorMessage>
					</params>
				</vpmeScriptNameFail>
				<serviceControlEnable>yes</serviceControlEnable>
			</rule>
			<rule>
				<serviceControlTable>userdb</serviceControlTable>
				<replyMailbox>_helpdesk</replyMailbox>
				<name>AWS Request Authorization</name>
				<condition>SUBJECT LIKE &apos;AWS Request Authorization Decision%&apos;</condition>
				<application>ITSM</application>
				<serviceControlEnable>yes</serviceControlEnable>
				<serviceControlTableKey>keysearch</serviceControlTableKey>
				<serviceControlTableMatchColumn>email</serviceControlTableMatchColumn>
				<serviceControlTableControl>webflag</serviceControlTableControl>
				<serviceControlTableControlBit>0</serviceControlTableControlBit>
				<serviceControlMatchWith>fromAddress</serviceControlMatchWith>
				<vpmeScriptNameOk name="arAuthorise" includeFiles="true">
					<params>
						<callref>CALLREF_VALUE(subject)</callref>
						<decision>TOKEN(subject, 0, 6)</decision>
						<comments>body</comments>
						<customerId>sc_keysearch</customerId>
						<customerFirstname>sc_firstname</customerFirstname>
						<customerLastname>sc_surname</customerLastname>
						<replyEmail>fromAddress</replyEmail>
						<replyMailbox>mailbox</replyMailbox>
						<replyTemplateOk>replyTemplateOk</replyTemplateOk>
						<replyTemplateFail>replyTemplateFail</replyTemplateFail>
						<msbSubject>subject</msbSubject>
					</params>
				</vpmeScriptNameOk>
				<vpmeScriptNameFail name="arRequestFail" includeFiles="true">
					<params>
						<replyEmail>fromAddress</replyEmail>
						<replyMailbox>mailbox</replyMailbox>
						<replyTemplateFail>replyTemplateFail</replyTemplateFail>
						<errorMessage>errorMessage</errorMessage>
					</params>
				</vpmeScriptNameFail>
				<replyTemplateOk>Confirmation of Call Update</replyTemplateOk>
				<replyTemplateFail>Call Update Request Rejected</replyTemplateFail>
			</rule>
		</rules>
	</AutoResponder>
	<SelfService>
		<CopyScript value="&amp;[InstallPath]\html\clisupp\php\copy_wss_settings.php"/>
	</SelfService>
	<PhpExtensions>
		<logging type="dword" value="0"/>
	</PhpExtensions>
	<RuntimeOptions value="1648"/>
</Config>
